{
  "date": "2025-08-20",
  "timestamp": "2025-08-20T19:49:35.194606",
  "timeframes": [
    "1D",
    "1W",
    "1M"
  ],
  "total_symbols": 304,
  "successful_fetches": 296,
  "failed_fetches": 8,
  "data": {
    "CSELK-AFSL.N0000": {
      "rsi_data": null,
      "status": "failed",
      "error": "Could not create Chrome driver",
      "timestamp": "2025-08-20T19:19:55.676841"
    },
    "CSELK-AEL.N0000": {
      "rsi_data": {
        "1D": 53.5,
        "1W": 73.9,
        "1M": 80.5
      },
      "status": "success",
      "successful_timeframes": 3,
      "timestamp": "2025-08-20T19:20:13.548510"
    },
    "CSELK-ABAN.N0000": {
      "rsi_data": {
        "1D": 81.8,
        "1W": 93.72,
        "1M": 87.76
      },
      "status": "success",
      "successful_timeframes": 3,
      "timestamp": "2025-08-20T19:20:13.594231"
    },
    "CSELK-ACL.N0000": {
      "rsi_data": {
        "1D": 69.25,
        "1W": 78.0,
        "1M": 79.09
      },
      "status": "success",
      "successful_timeframes": 3,
      "timestamp": "2025-08-20T19:20:24.707655"
    },
    "CSELK-APLA.N0000": {
      "rsi_data": {
        "1D": 88.92,
        "1W": 84.98,
        "1M": 80.18
      },
      "status": "success",
      "successful_timeframes": 3,
      "timestamp": "2025-08-20T19:20:25.028561"
    },
    "CSELK-ACME.N0000": {
      "rsi_data": {
        "1D": 54.8,
        "1W": 56.5,
        "1M": 50.6
      },
      "status": "success",
      "successful_timeframes": 3,
      "timestamp": "2025-08-20T19:20:35.921415"
    },
    "CSELK-AGAL.N0000": {
      "rsi_data": {
        "1D": 49.9,
        "1W": 65.8,
        "1M": 65.9
      },
      "status": "success",
      "successful_timeframes": 3,
      "timestamp": "2025-08-20T19:20:36.109768"
    },
    "CSELK-AGST.N0000": {
      "rsi_data": {
        "1D": 53.4,
        "1W": 53.9,
        "1M": 48.4
      },
      "status": "success",
      "successful_timeframes": 3,
      "timestamp": "2025-08-20T19:20:47.068836"
    },
    "CSELK-AGST.X0000": {
      "rsi_data": {
        "1D": 83.2,
        "1W": 82.9,
        "1M": null
      },
      "status": "success",
      "successful_timeframes": 2,
      "timestamp": "2025-08-20T19:20:52.536061"
    },
    "CSELK-AHUN.N0000": {
      "rsi_data": {
        "1D": 64.7,
        "1W": 62.2,
        "1M": 65.4
      },
      "status": "success",
      "successful_timeframes": 3,
      "timestamp": "2025-08-20T19:20:58.052609"
    },
    "CSELK-SPEN.N0000": {
      "rsi_data": {
        "1D": 70.6,
        "1W": 62.3,
        "1M": 60.92
      },
      "status": "success",
      "successful_timeframes": 3,
      "timestamp": "2025-08-20T19:21:09.080212"
    },
    "CSELK-ASPM.N0000": {
      "rsi_data": null,
      "status": "failed",
      "error": "Error: Message: \nStacktrace:\n#0 0x55cb17da202a <unknown>\n#1 0x55cb17841a70 <unknown>\n#2 0x55cb17893907 <unknown>\n#3 0x55cb17893b01 <unknown>\n#4 0x55cb178e1d54 <unknown>\n#5 0x55cb178b940d <unknown>\n#6 0x55cb178df14f <unknown>\n#7 0x55cb178b91b3 <unknown>\n#8 0x55cb1788559b <unknown>\n#9 0x55cb17886971 <unknown>\n#10 0x55cb17d671fb <unknown>\n#11 0x55cb17d6af49 <unknown>\n#12 0x55cb17d4e2d9 <unknown>\n#13 0x55cb17d6baf8 <unknown>\n#14 0x55cb17d32bbf <unknown>\n#15 0x55cb17d8f0b8 <unknown>\n#16 0x55cb17d8f296 <unknown>\n#17 0x55cb17da1006 <unknown>\n#18 0x7f66bcc9caa4 <unknown>\n#19 0x7f66bcd29c3c <unknown>\n",
      "timestamp": "2025-08-20T19:21:18.388887"
    },
    "CSELK-ALLI.N0000": {
      "rsi_data": {
        "1D": 33.33,
        "1W": 65.47,
        "1M": 78.69
      },
      "status": "success",
      "successful_timeframes": 3,
      "timestamp": "2025-08-20T19:21:23.108523"
    },
    "CSELK-AFS.N0000": {
      "rsi_data": {
        "1D": 74.6,
        "1W": 82.8,
        "1M": 92.7
      },
      "status": "success",
      "successful_timeframes": 3,
      "timestamp": "2025-08-20T19:21:29.469764"
    },
    "CSELK-ALUM.N0000": {
      "rsi_data": {
        "1D": 60.2,
        "1W": 63.1,
        "1M": 68.9
      },
      "status": "success",
      "successful_timeframes": 3,
      "timestamp": "2025-08-20T19:21:34.096134"
    },
    "CSELK-ABL.N0000": {
      "rsi_data": {
        "1D": 88.1,
        "1W": 79.8,
        "1M": 62.2
      },
      "status": "success",
      "successful_timeframes": 3,
      "timestamp": "2025-08-20T19:21:40.406722"
    },
    "CSELK-ATL.N0000": {
      "rsi_data": {
        "1D": 84.8,
        "1W": 83.4,
        "1M": 81.8
      },
      "status": "success",
      "successful_timeframes": 3,
      "timestamp": "2025-08-20T19:21:45.274309"
    },
    "CSELK-ATLL.N0000": {
      "rsi_data": {
        "1D": 77.4,
        "1W": 78.6,
        "1M": 74.3
      },
      "status": "success",
      "successful_timeframes": 3,
      "timestamp": "2025-08-20T19:21:51.289541"
    },
    "CSELK-GREG.N0000": {
      "rsi_data": {
        "1D": 76.86,
        "1W": 80.0,
        "1M": 78.81
      },
      "status": "success",
      "successful_timeframes": 3,
      "timestamp": "2025-08-20T19:21:56.248960"
    },
    "CSELK-ALHP.N0000": {
      "rsi_data": {
        "1D": 39.6,
        "1W": 38.5,
        "1M": 43.4
      },
      "status": "success",
      "successful_timeframes": 3,
      "timestamp": "2025-08-20T19:22:07.282985"
    },
    "CSELK-AMCL.N0000": {
      "rsi_data": null,
      "status": "failed",
      "error": "Error: Message: \nStacktrace:\n#0 0x558688ab502a <unknown>\n#1 0x558688554a70 <unknown>\n#2 0x5586885a6907 <unknown>\n#3 0x5586885a6b01 <unknown>\n#4 0x5586885f4d54 <unknown>\n#5 0x5586885cc40d <unknown>\n#6 0x5586885f214f <unknown>\n#7 0x5586885cc1b3 <unknown>\n#8 0x55868859859b <unknown>\n#9 0x558688599971 <unknown>\n#10 0x558688a7a1fb <unknown>\n#11 0x558688a7df49 <unknown>\n#12 0x558688a612d9 <unknown>\n#13 0x558688a7eaf8 <unknown>\n#14 0x558688a45bbf <unknown>\n#15 0x558688aa20b8 <unknown>\n#16 0x558688aa2296 <unknown>\n#17 0x558688ab4006 <unknown>\n#18 0x7fa17be9caa4 <unknown>\n#19 0x7fa17bf29c3c <unknown>\n",
      "timestamp": "2025-08-20T19:22:17.098909"
    },
    "CSELK-AINS.N0000": {
      "rsi_data": {
        "1D": 57.0,
        "1W": 68.2,
        "1M": 72.9
      },
      "status": "success",
      "successful_timeframes": 3,
      "timestamp": "2025-08-20T19:22:18.209680"
    },
    "CSELK-AAF.N0000": {
      "rsi_data": {
        "1D": 51.6,
        "1W": 75.6,
        "1M": 83.7
      },
      "status": "success",
      "successful_timeframes": 3,
      "timestamp": "2025-08-20T19:22:28.239049"
    },
    "CSELK-AAF.P0000": {
      "rsi_data": {
        "1D": 56.3,
        "1W": 68.0,
        "1M": 80.1
      },
      "status": "success",
      "successful_timeframes": 3,
      "timestamp": "2025-08-20T19:22:29.428435"
    },
    "CSELK-ACAP.N0000": {
      "rsi_data": {
        "1D": 65.0,
        "1W": 63.0,
        "1M": 62.3
      },
      "status": "success",
      "successful_timeframes": 3,
      "timestamp": "2025-08-20T19:22:39.362322"
    },
    "CSELK-ASIY.N0000": {
      "rsi_data": {
        "1D": 52.7,
        "1W": 61.0,
        "1M": 68.3
      },
      "status": "success",
      "successful_timeframes": 3,
      "timestamp": "2025-08-20T19:22:40.580963"
    },
    "CSELK-AHPL.N0000": {
      "rsi_data": {
        "1D": 55.5,
        "1W": 65.5,
        "1M": 60.4
      },
      "status": "success",
      "successful_timeframes": 3,
      "timestamp": "2025-08-20T19:22:50.431394"
    },
    "CSELK-AMSL.N0000": {
      "rsi_data": {
        "1D": 54.6,
        "1W": 69.1,
        "1M": 59.2
      },
      "status": "success",
      "successful_timeframes": 3,
      "timestamp": "2025-08-20T19:22:51.716838"
    },
    "CSELK-ASIR.N0000": {
      "rsi_data": {
        "1D": 58.1,
        "1W": 77.0,
        "1M": 71.5
      },
      "status": "success",
      "successful_timeframes": 3,
      "timestamp": "2025-08-20T19:23:01.564617"
    },
    "CSELK-AMF.N0000": {
      "rsi_data": {
        "1D": 79.3,
        "1W": 94.2,
        "1M": 93.6
      },
      "status": "success",
      "successful_timeframes": 3,
      "timestamp": "2025-08-20T19:23:02.893792"
    },
    "CSELK-AGPL.N0000": {
      "rsi_data": {
        "1D": 57.3,
        "1W": 65.0,
        "1M": 79.2
      },
      "status": "success",
      "successful_timeframes": 3,
      "timestamp": "2025-08-20T19:23:12.949780"
    },
    "CSELK-BPPL.N0000": {
      "rsi_data": {
        "1D": 47.3,
        "1W": 48.6,
        "1M": 48.3
      },
      "status": "success",
      "successful_timeframes": 3,
      "timestamp": "2025-08-20T19:23:13.996043"
    },
    "CSELK-BFL.N0000": {
      "rsi_data": {
        "1D": 41.93,
        "1W": 59.17,
        "1M": 60.2
      },
      "status": "success",
      "successful_timeframes": 3,
      "timestamp": "2025-08-20T19:23:24.009922"
    },
    "CSELK-BALA.N0000": {
      "rsi_data": {
        "1D": 66.5,
        "1W": 67.0,
        "1M": 65.7
      },
      "status": "success",
      "successful_timeframes": 3,
      "timestamp": "2025-08-20T19:23:25.068824"
    },
    "CSELK-BRR.N0000": {
      "rsi_data": {
        "1D": 56.1,
        "1W": 67.7,
        "1M": 74.2
      },
      "status": "success",
      "successful_timeframes": 3,
      "timestamp": "2025-08-20T19:23:35.169697"
    },
    "CSELK-BERU.N0000": {
      "rsi_data": {
        "1D": 50.6,
        "1W": 53.2,
        "1M": 66.9
      },
      "status": "success",
      "successful_timeframes": 3,
      "timestamp": "2025-08-20T19:23:36.239974"
    },
    "CSELK-BLI.N0000": {
      "rsi_data": {
        "1D": 48.4,
        "1W": 48.3,
        "1M": 36.9
      },
      "status": "success",
      "successful_timeframes": 3,
      "timestamp": "2025-08-20T19:23:46.462383"
    },
    "CSELK-BLUE.X0000": {
      "rsi_data": {
        "1D": 47.0,
        "1W": 44.1,
        "1M": 45.3
      },
      "status": "success",
      "successful_timeframes": 3,
      "timestamp": "2025-08-20T19:23:47.593426"
    },
    "CSELK-BLUE.N0000": {
      "rsi_data": {
        "1D": 43.0,
        "1W": 28.1,
        "1M": 41.1
      },
      "status": "success",
      "successful_timeframes": 3,
      "timestamp": "2025-08-20T19:23:57.606792"
    },
    "CSELK-BOGA.N0000": {
      "rsi_data": {
        "1D": 68.1,
        "1W": 70.2,
        "1M": 72.5
      },
      "status": "success",
      "successful_timeframes": 3,
      "timestamp": "2025-08-20T19:24:00.105770"
    },
    "CSELK-BOPL.N0000": {
      "rsi_data": {
        "1D": 60.1,
        "1W": 72.5,
        "1M": 70.7
      },
      "status": "success",
      "successful_timeframes": 3,
      "timestamp": "2025-08-20T19:24:08.587513"
    },
    "CSELK-BRWN.N0000": {
      "rsi_data": {
        "1D": 46.73,
        "1W": 52.23,
        "1M": 58.76
      },
      "status": "success",
      "successful_timeframes": 3,
      "timestamp": "2025-08-20T19:24:11.056477"
    },
    "CSELK-BBH.N0000": {
      "rsi_data": {
        "1D": 63.5,
        "1W": 65.7,
        "1M": 70.1
      },
      "status": "success",
      "successful_timeframes": 3,
      "timestamp": "2025-08-20T19:24:19.576020"
    },
    "CSELK-BIL.N0000": {
      "rsi_data": {
        "1D": 44.0,
        "1W": 49.1,
        "1M": 54.1
      },
      "status": "success",
      "successful_timeframes": 3,
      "timestamp": "2025-08-20T19:24:21.918192"
    },
    "CSELK-BUKI.N0000": {
      "rsi_data": {
        "1D": 83.2,
        "1W": 81.26,
        "1M": 87.25
      },
      "status": "success",
      "successful_timeframes": 3,
      "timestamp": "2025-08-20T19:24:30.996212"
    },
    "CSELK-COLO.N0000": {
      "rsi_data": {
        "1D": 54.41,
        "1W": 71.86,
        "1M": 89.68
      },
      "status": "success",
      "successful_timeframes": 3,
      "timestamp": "2025-08-20T19:24:32.768249"
    },
    "CSELK-CTHR.N0000": {
      "rsi_data": {
        "1D": 70.31,
        "1W": 90.04,
        "1M": 93.19
      },
      "status": "success",
      "successful_timeframes": 3,
      "timestamp": "2025-08-20T19:24:41.989058"
    },
    "CSELK-CTLD.N0000": {
      "rsi_data": {
        "1D": 57.1,
        "1W": 62.1,
        "1M": 61.7
      },
      "status": "success",
      "successful_timeframes": 3,
      "timestamp": "2025-08-20T19:24:43.706958"
    },
    "CSELK-CWM.N0000": {
      "rsi_data": {
        "1D": 43.07,
        "1W": 52.48,
        "1M": 65.73
      },
      "status": "success",
      "successful_timeframes": 3,
      "timestamp": "2025-08-20T19:24:52.937408"
    },
    "CSELK-CSLK.N0000": {
      "rsi_data": {
        "1D": 64.7,
        "1W": 70.1,
        "1M": null
      },
      "status": "success",
      "successful_timeframes": 2,
      "timestamp": "2025-08-20T19:24:59.913065"
    },
    "CSELK-CALI.U0000": {
      "rsi_data": {
        "1D": 47.7,
        "1W": 49.4,
        "1M": 32.1
      },
      "status": "success",
      "successful_timeframes": 3,
      "timestamp": "2025-08-20T19:25:10.860027"
    },
    "CSELK-CALC.U0000": {
      "rsi_data": {
        "1D": 49.4,
        "1W": 33.7,
        "1M": null
      },
      "status": "success",
      "successful_timeframes": 2,
      "timestamp": "2025-08-20T19:25:19.972722"
    },
    "CSELK-CALT.N0000": {
      "rsi_data": {
        "1D": 69.4,
        "1W": 72.9,
        "1M": 62.1
      },
      "status": "success",
      "successful_timeframes": 3,
      "timestamp": "2025-08-20T19:25:30.981782"
    },
    "CSELK-CARG.N0000": {
      "rsi_data": {
        "1D": 73.97,
        "1W": 86.6,
        "1M": 91.53
      },
      "status": "success",
      "successful_timeframes": 3,
      "timestamp": "2025-08-20T19:25:41.881945"
    },
    "CSELK-CALH.N0000": {
      "rsi_data": {
        "1D": 66.8,
        "1W": null,
        "1M": null
      },
      "status": "success",
      "successful_timeframes": 1,
      "timestamp": "2025-08-20T19:25:43.033961"
    },
    "CSELK-CBNK.N0000": {
      "rsi_data": {
        "1D": 48.0,
        "1W": 60.0,
        "1M": 60.9
      },
      "status": "success",
      "successful_timeframes": 3,
      "timestamp": "2025-08-20T19:25:52.850720"
    },
    "CSELK-CABO.N0000": {
      "rsi_data": {
        "1D": 60.37,
        "1W": 72.57,
        "1M": 83.51
      },
      "status": "success",
      "successful_timeframes": 3,
      "timestamp": "2025-08-20T19:25:54.016913"
    },
    "CSELK-CARS.N0000": {
      "rsi_data": {
        "1D": 89.78,
        "1W": 90.75,
        "1M": 89.09
      },
      "status": "success",
      "successful_timeframes": 3,
      "timestamp": "2025-08-20T19:26:03.912096"
    },
    "CSELK-CFIN.N0000": {
      "rsi_data": {
        "1D": 46.48,
        "1W": 70.66,
        "1M": 76.9
      },
      "status": "success",
      "successful_timeframes": 3,
      "timestamp": "2025-08-20T19:26:05.084338"
    },
    "CSELK-CIND.N0000": {
      "rsi_data": {
        "1D": 43.07,
        "1W": 60.27,
        "1M": 63.75
      },
      "status": "success",
      "successful_timeframes": 3,
      "timestamp": "2025-08-20T19:26:15.004509"
    },
    "CSELK-CINS.X0000": {
      "rsi_data": {
        "1D": 62.69,
        "1W": 73.36,
        "1M": 79.02
      },
      "status": "success",
      "successful_timeframes": 3,
      "timestamp": "2025-08-20T19:26:21.741156"
    },
    "CSELK-CINS.N0000": {
      "rsi_data": {
        "1D": 51.33,
        "1W": 54.31,
        "1M": 59.64
      },
      "status": "success",
      "successful_timeframes": 3,
      "timestamp": "2025-08-20T19:26:25.963827"
    },
    "CSELK-BREW.N0000": {
      "rsi_data": {
        "1D": 55.14,
        "1W": 56.4,
        "1M": 71.0
      },
      "status": "success",
      "successful_timeframes": 3,
      "timestamp": "2025-08-20T19:26:32.670900"
    },
    "CSELK-CCS.N0000": {
      "rsi_data": {
        "1D": 45.4,
        "1W": 63.99,
        "1M": 75.31
      },
      "status": "success",
      "successful_timeframes": 3,
      "timestamp": "2025-08-20T19:26:36.927025"
    },
    "CSELK-GRAN.N0000": {
      "rsi_data": {
        "1D": 53.7,
        "1W": 77.47,
        "1M": 86.66
      },
      "status": "success",
      "successful_timeframes": 3,
      "timestamp": "2025-08-20T19:26:43.653769"
    },
    "CSELK-GUAR.N0000": {
      "rsi_data": {
        "1D": 69.07,
        "1W": 80.03,
        "1M": 80.18
      },
      "status": "success",
      "successful_timeframes": 3,
      "timestamp": "2025-08-20T19:26:47.919789"
    },
    "CSELK-CHL.X0000": {
      "rsi_data": {
        "1D": 72.96,
        "1W": 86.71,
        "1M": 76.05
      },
      "status": "success",
      "successful_timeframes": 3,
      "timestamp": "2025-08-20T19:26:54.727530"
    },
    "CSELK-CHL.N0000": {
      "rsi_data": {
        "1D": 66.29,
        "1W": 71.98,
        "1M": 78.13
      },
      "status": "success",
      "successful_timeframes": 3,
      "timestamp": "2025-08-20T19:26:58.919043"
    },
    "CSELK-CHOT.N0000": {
      "rsi_data": {
        "1D": 68.5,
        "1W": 63.0,
        "1M": 64.4
      },
      "status": "success",
      "successful_timeframes": 3,
      "timestamp": "2025-08-20T19:27:05.754333"
    },
    "CSELK-CINV.N0000": {
      "rsi_data": {
        "1D": 72.54,
        "1W": 80.45,
        "1M": 78.75
      },
      "status": "success",
      "successful_timeframes": 3,
      "timestamp": "2025-08-20T19:27:09.815352"
    },
    "CSELK-KZOO.N0000": {
      "rsi_data": {
        "1D": 62.8,
        "1W": 65.9,
        "1M": 61.9
      },
      "status": "success",
      "successful_timeframes": 3,
      "timestamp": "2025-08-20T19:27:16.664995"
    },
    "CSELK-CPRT.N0000": {
      "rsi_data": {
        "1D": 65.29,
        "1W": 64.79,
        "1M": 62.13
      },
      "status": "success",
      "successful_timeframes": 3,
      "timestamp": "2025-08-20T19:27:20.815772"
    },
    "CSELK-CTBL.N0000": {
      "rsi_data": {
        "1D": 53.1,
        "1W": 59.9,
        "1M": 63.0
      },
      "status": "success",
      "successful_timeframes": 3,
      "timestamp": "2025-08-20T19:27:27.676990"
    },
    "CSELK-CTC.N0000": {
      "rsi_data": {
        "1D": 86.9,
        "1W": 73.41,
        "1M": 77.56
      },
      "status": "success",
      "successful_timeframes": 3,
      "timestamp": "2025-08-20T19:27:31.833217"
    },
    "CSELK-CHMX.N0000": {
      "rsi_data": {
        "1D": 49.44,
        "1W": 59.36,
        "1M": 68.67
      },
      "status": "success",
      "successful_timeframes": 3,
      "timestamp": "2025-08-20T19:27:38.587057"
    },
    "CSELK-LLUB.N0000": {
      "rsi_data": {
        "1D": 69.0,
        "1W": 73.86,
        "1M": 73.39
      },
      "status": "success",
      "successful_timeframes": 3,
      "timestamp": "2025-08-20T19:27:42.670400"
    },
    "CSELK-CWL.N0000": {
      "rsi_data": {
        "1D": 48.4,
        "1W": 52.1,
        "1M": 50.2
      },
      "status": "success",
      "successful_timeframes": 3,
      "timestamp": "2025-08-20T19:27:49.516175"
    },
    "CSELK-CIC.X0000": {
      "rsi_data": {
        "1D": 61.14,
        "1W": 68.38,
        "1M": 75.47
      },
      "status": "success",
      "successful_timeframes": 3,
      "timestamp": "2025-08-20T19:27:53.638128"
    },
    "CSELK-CIC.N0000": {
      "rsi_data": {
        "1D": 47.48,
        "1W": 61.46,
        "1M": 75.96
      },
      "status": "success",
      "successful_timeframes": 3,
      "timestamp": "2025-08-20T19:28:00.620000"
    },
    "CSELK-CDB.N0000": {
      "rsi_data": {
        "1D": 51.79,
        "1W": 75.8,
        "1M": 78.39
      },
      "status": "success",
      "successful_timeframes": 3,
      "timestamp": "2025-08-20T19:28:04.557393"
    },
    "CSELK-CDB.X0000": {
      "rsi_data": {
        "1D": 50.93,
        "1W": 70.82,
        "1M": 86.77
      },
      "status": "success",
      "successful_timeframes": 3,
      "timestamp": "2025-08-20T19:28:11.630179"
    },
    "CSELK-REEF.N0000": {
      "rsi_data": {
        "1D": 54.5,
        "1W": 52.5,
        "1M": 42.7
      },
      "status": "success",
      "successful_timeframes": 3,
      "timestamp": "2025-08-20T19:28:15.526911"
    },
    "CSELK-CHOU.N0000": {
      "rsi_data": {
        "1D": 32.1,
        "1W": 31.8,
        "1M": 33.0
      },
      "status": "success",
      "successful_timeframes": 3,
      "timestamp": "2025-08-20T19:28:22.758164"
    },
    "CSELK-COOP.N0000": {
      "rsi_data": {
        "1D": 58.8,
        "1W": 70.5,
        "1M": 63.5
      },
      "status": "success",
      "successful_timeframes": 3,
      "timestamp": "2025-08-20T19:28:26.517020"
    },
    "CSELK-PHAR.N0000": {
      "rsi_data": {
        "1D": 65.78,
        "1W": 77.49,
        "1M": 78.23
      },
      "status": "success",
      "successful_timeframes": 3,
      "timestamp": "2025-08-20T19:28:33.727430"
    },
    "CSELK-DOCK.N0000": {
      "rsi_data": {
        "1D": 60.96,
        "1W": 67.6,
        "1M": 73.35
      },
      "status": "success",
      "successful_timeframes": 3,
      "timestamp": "2025-08-20T19:28:37.529943"
    },
    "CSELK-CFI.N0000": {
      "rsi_data": {
        "1D": 66.06,
        "1W": 86.08,
        "1M": 91.75
      },
      "status": "success",
      "successful_timeframes": 3,
      "timestamp": "2025-08-20T19:28:44.885137"
    },
    "CSELK-CIT.N0000": {
      "rsi_data": {
        "1D": 70.39,
        "1W": 81.13,
        "1M": 85.0
      },
      "status": "success",
      "successful_timeframes": 3,
      "timestamp": "2025-08-20T19:28:48.518164"
    },
    "CSELK-CLND.N0000": {
      "rsi_data": {
        "1D": 56.8,
        "1W": 71.9,
        "1M": 69.0
      },
      "status": "success",
      "successful_timeframes": 3,
      "timestamp": "2025-08-20T19:28:55.770734"
    },
    "CSELK-COMB.N0000": {
      "rsi_data": {
        "1D": 89.01,
        "1W": 86.01,
        "1M": 80.98
      },
      "status": "success",
      "successful_timeframes": 3,
      "timestamp": "2025-08-20T19:28:59.461421"
    },
    "CSELK-COMB.X0000": {
      "rsi_data": {
        "1D": 89.24,
        "1W": 86.62,
        "1M": 80.31
      },
      "status": "success",
      "successful_timeframes": 3,
      "timestamp": "2025-08-20T19:29:06.999295"
    },
    "CSELK-COCR.N0000": {
      "rsi_data": {
        "1D": 82.4,
        "1W": 89.47,
        "1M": 87.54
      },
      "status": "success",
      "successful_timeframes": 3,
      "timestamp": "2025-08-20T19:29:10.451085"
    },
    "CSELK-COMD.N0000": {
      "rsi_data": {
        "1D": 56.06,
        "1W": 75.71,
        "1M": 78.65
      },
      "status": "success",
      "successful_timeframes": 3,
      "timestamp": "2025-08-20T19:29:18.043406"
    },
    "CSELK-SOY.N0000": {
      "rsi_data": {
        "1D": 68.97,
        "1W": 76.35,
        "1M": 78.24
      },
      "status": "success",
      "successful_timeframes": 3,
      "timestamp": "2025-08-20T19:29:21.594060"
    },
    "CSELK-DPL.N0000": {
      "rsi_data": {
        "1D": 51.5,
        "1W": 49.2,
        "1M": 50.1
      },
      "status": "success",
      "successful_timeframes": 3,
      "timestamp": "2025-08-20T19:29:29.209609"
    },
    "CSELK-DFCC.N0000": {
      "rsi_data": {
        "1D": 83.12,
        "1W": 83.83,
        "1M": 78.55
      },
      "status": "success",
      "successful_timeframes": 3,
      "timestamp": "2025-08-20T19:29:32.637612"
    },
    "CSELK-DIAL.N0000": {
      "rsi_data": {
        "1D": 86.1,
        "1W": 89.9,
        "1M": 81.8
      },
      "status": "success",
      "successful_timeframes": 3,
      "timestamp": "2025-08-20T19:29:40.205061"
    },
    "CSELK-CALF.N0000": {
      "rsi_data": {
        "1D": 63.8,
        "1W": 72.4,
        "1M": 67.4
      },
      "status": "success",
      "successful_timeframes": 3,
      "timestamp": "2025-08-20T19:29:43.734842"
    },
    "CSELK-DIMO.N0000": {
      "rsi_data": {
        "1D": 51.54,
        "1W": 61.99,
        "1M": 69.41
      },
      "status": "success",
      "successful_timeframes": 3,
      "timestamp": "2025-08-20T19:29:51.109700"
    },
    "CSELK-PKME.N0000": {
      "rsi_data": {
        "1D": 77.92,
        "1W": 89.74,
        "1M": null
      },
      "status": "success",
      "successful_timeframes": 2,
      "timestamp": "2025-08-20T19:29:59.780834"
    },
    "CSELK-CTEA.N0000": {
      "rsi_data": {
        "1D": 52.5,
        "1W": 60.42,
        "1M": 60.52
      },
      "status": "success",
      "successful_timeframes": 3,
      "timestamp": "2025-08-20T19:30:03.122875"
    },
    "CSELK-DIPD.N0000": {
      "rsi_data": {
        "1D": 45.8,
        "1W": 56.3,
        "1M": 66.7
      },
      "status": "success",
      "successful_timeframes": 3,
      "timestamp": "2025-08-20T19:30:10.698672"
    },
    "CSELK-DIST.N0000": {
      "rsi_data": {
        "1D": 52.8,
        "1W": 68.2,
        "1M": 78.1
      },
      "status": "success",
      "successful_timeframes": 3,
      "timestamp": "2025-08-20T19:30:14.112310"
    },
    "CSELK-STAF.N0000": {
      "rsi_data": {
        "1D": 81.3,
        "1W": 69.9,
        "1M": 69.8
      },
      "status": "success",
      "successful_timeframes": 3,
      "timestamp": "2025-08-20T19:30:21.645324"
    },
    "CSELK-ASCO.N0000": {
      "rsi_data": {
        "1D": 52.5,
        "1W": 67.8,
        "1M": 69.9
      },
      "status": "success",
      "successful_timeframes": 3,
      "timestamp": "2025-08-20T19:30:25.046072"
    },
    "CSELK-ASHO.N0000": {
      "rsi_data": {
        "1D": 60.37,
        "1W": 83.47,
        "1M": 85.98
      },
      "status": "success",
      "successful_timeframes": 3,
      "timestamp": "2025-08-20T19:30:32.552682"
    },
    "CSELK-ASPH.N0000": {
      "rsi_data": {
        "1D": 45.0,
        "1W": 49.4,
        "1M": 50.8
      },
      "status": "success",
      "successful_timeframes": 3,
      "timestamp": "2025-08-20T19:30:36.219094"
    },
    "CSELK-BFN.N0000": {
      "rsi_data": {
        "1D": 80.4,
        "1W": 90.2,
        "1M": 92.7
      },
      "status": "success",
      "successful_timeframes": 3,
      "timestamp": "2025-08-20T19:30:43.645348"
    },
    "CSELK-CERA.N0000": {
      "rsi_data": {
        "1D": 49.11,
        "1W": 65.64,
        "1M": 71.03
      },
      "status": "success",
      "successful_timeframes": 3,
      "timestamp": "2025-08-20T19:30:47.186406"
    },
    "CSELK-CFVF.N0000": {
      "rsi_data": {
        "1D": 84.3,
        "1W": 80.3,
        "1M": 69.1
      },
      "status": "success",
      "successful_timeframes": 3,
      "timestamp": "2025-08-20T19:30:54.578411"
    },
    "CSELK-CITH.N0000": {
      "rsi_data": {
        "1D": 58.0,
        "1W": 55.8,
        "1M": 43.8
      },
      "status": "success",
      "successful_timeframes": 3,
      "timestamp": "2025-08-20T19:30:58.134625"
    },
    "CSELK-CONN.N0000": {
      "rsi_data": {
        "1D": 48.3,
        "1W": 56.1,
        "1M": 61.5
      },
      "status": "success",
      "successful_timeframes": 3,
      "timestamp": "2025-08-20T19:31:05.572382"
    },
    "CSELK-CSF.N0000": {
      "rsi_data": {
        "1D": 46.4,
        "1W": 37.1,
        "1M": 34.5
      },
      "status": "success",
      "successful_timeframes": 3,
      "timestamp": "2025-08-20T19:31:09.128535"
    },
    "CSELK-EAST.N0000": {
      "rsi_data": {
        "1D": 83.4,
        "1W": 89.7,
        "1M": 94.0
      },
      "status": "success",
      "successful_timeframes": 3,
      "timestamp": "2025-08-20T19:31:16.497614"
    },
    "CSELK-EBCR.N0000": {
      "rsi_data": {
        "1D": 55.9,
        "1W": 72.4,
        "1M": 80.9
      },
      "status": "success",
      "successful_timeframes": 3,
      "timestamp": "2025-08-20T19:31:20.067254"
    },
    "CSELK-ECL.N0000": {
      "rsi_data": {
        "1D": 42.5,
        "1W": 48.4,
        "1M": 48.7
      },
      "status": "success",
      "successful_timeframes": 3,
      "timestamp": "2025-08-20T19:31:27.450826"
    },
    "CSELK-EDEN.N0000": {
      "rsi_data": {
        "1D": 53.7,
        "1W": 52.2,
        "1M": 52.8
      },
      "status": "success",
      "successful_timeframes": 3,
      "timestamp": "2025-08-20T19:31:31.091655"
    },
    "CSELK-ELPL.N0000": {
      "rsi_data": {
        "1D": 67.75,
        "1W": 78.78,
        "1M": 73.73
      },
      "status": "success",
      "successful_timeframes": 3,
      "timestamp": "2025-08-20T19:31:38.376392"
    },
    "CSELK-EMER.N0000": {
      "rsi_data": {
        "1D": 48.2,
        "1W": 54.1,
        "1M": 55.2
      },
      "status": "success",
      "successful_timeframes": 3,
      "timestamp": "2025-08-20T19:31:41.910837"
    },
    "CSELK-EML.N0000": {
      "rsi_data": {
        "1D": 47.9,
        "1W": 54.0,
        "1M": 43.8
      },
      "status": "success",
      "successful_timeframes": 3,
      "timestamp": "2025-08-20T19:31:49.299544"
    },
    "CSELK-ETWO.N0000": {
      "rsi_data": {
        "1D": 54.9,
        "1W": 58.3,
        "1M": 59.9
      },
      "status": "success",
      "successful_timeframes": 3,
      "timestamp": "2025-08-20T19:31:52.798974"
    },
    "CSELK-EXT.N0000": {
      "rsi_data": {
        "1D": 53.7,
        "1W": 55.5,
        "1M": 46.8
      },
      "status": "success",
      "successful_timeframes": 3,
      "timestamp": "2025-08-20T19:32:00.227619"
    },
    "CSELK-FCT.N0000": {
      "rsi_data": {
        "1D": 72.0,
        "1W": 80.5,
        "1M": 62.4
      },
      "status": "success",
      "successful_timeframes": 3,
      "timestamp": "2025-08-20T19:32:03.753159"
    },
    "CSELK-GEST.N0000": {
      "rsi_data": {
        "1D": 49.73,
        "1W": 68.04,
        "1M": 70.83
      },
      "status": "success",
      "successful_timeframes": 3,
      "timestamp": "2025-08-20T19:32:11.258570"
    },
    "CSELK-GHLL.N0000": {
      "rsi_data": {
        "1D": 59.2,
        "1W": 65.6,
        "1M": 62.4
      },
      "status": "success",
      "successful_timeframes": 3,
      "timestamp": "2025-08-20T19:32:14.628571"
    },
    "CSELK-HAPU.N0000": {
      "rsi_data": {
        "1D": 53.0,
        "1W": 57.7,
        "1M": 59.8
      },
      "status": "success",
      "successful_timeframes": 3,
      "timestamp": "2025-08-20T19:32:22.232986"
    },
    "CSELK-HARI.N0000": {
      "rsi_data": {
        "1D": 48.56,
        "1W": 48.87,
        "1M": 47.79
      },
      "status": "success",
      "successful_timeframes": 3,
      "timestamp": "2025-08-20T19:32:25.559148"
    },
    "CSELK-HASU.N0000": {
      "rsi_data": {
        "1D": 50.08,
        "1W": 67.75,
        "1M": 72.57
      },
      "status": "success",
      "successful_timeframes": 3,
      "timestamp": "2025-08-20T19:32:33.236662"
    },
    "CSELK-HAYC.N0000": {
      "rsi_data": {
        "1D": 47.4,
        "1W": 58.0,
        "1M": 61.9
      },
      "status": "success",
      "successful_timeframes": 3,
      "timestamp": "2025-08-20T19:32:36.658408"
    },
    "CSELK-HAYL.N0000": {
      "rsi_data": {
        "1D": 48.33,
        "1W": 66.53,
        "1M": 73.85
      },
      "status": "success",
      "successful_timeframes": 3,
      "timestamp": "2025-08-20T19:32:44.367770"
    },
    "CSELK-HBS.N0000": {
      "rsi_data": {
        "1D": 50.9,
        "1W": 54.8,
        "1M": 37.6
      },
      "status": "success",
      "successful_timeframes": 3,
      "timestamp": "2025-08-20T19:32:47.650993"
    },
    "CSELK-HDFC.N0000": {
      "rsi_data": {
        "1D": 64.2,
        "1W": 59.3,
        "1M": 62.6
      },
      "status": "success",
      "successful_timeframes": 3,
      "timestamp": "2025-08-20T19:32:55.403161"
    },
    "CSELK-HELA.N0000": {
      "rsi_data": {
        "1D": 47.0,
        "1W": 39.5,
        "1M": 32.2
      },
      "status": "success",
      "successful_timeframes": 3,
      "timestamp": "2025-08-20T19:32:58.767488"
    },
    "CSELK-HEXP.N0000": {
      "rsi_data": {
        "1D": 63.2,
        "1W": 71.1,
        "1M": 61.1
      },
      "status": "success",
      "successful_timeframes": 3,
      "timestamp": "2025-08-20T19:33:06.480758"
    },
    "CSELK-HHL.N0000": {
      "rsi_data": {
        "1D": 37.4,
        "1W": 62.9,
        "1M": 79.0
      },
      "status": "success",
      "successful_timeframes": 3,
      "timestamp": "2025-08-20T19:33:09.744709"
    },
    "CSELK-HNB.N0000": {
      "rsi_data": {
        "1D": 89.32,
        "1W": 83.26,
        "1M": 76.96
      },
      "status": "success",
      "successful_timeframes": 3,
      "timestamp": "2025-08-20T19:33:17.410865"
    },
    "CSELK-HNB.X0000": {
      "rsi_data": {
        "1D": 82.88,
        "1W": 74.7,
        "1M": 75.73
      },
      "status": "success",
      "successful_timeframes": 3,
      "timestamp": "2025-08-20T19:33:20.759177"
    },
    "CSELK-HNBF.N0000": {
      "rsi_data": {
        "1D": 79.3,
        "1W": 84.5,
        "1M": 72.9
      },
      "status": "success",
      "successful_timeframes": 3,
      "timestamp": "2025-08-20T19:33:28.447806"
    },
    "CSELK-HNBF.R0000": {
      "rsi_data": null,
      "status": "failed",
      "error": "Error: Message: \nStacktrace:\n#0 0x55eb3c48f02a <unknown>\n#1 0x55eb3bf2ea70 <unknown>\n#2 0x55eb3bf80907 <unknown>\n#3 0x55eb3bf80b01 <unknown>\n#4 0x55eb3bfced54 <unknown>\n#5 0x55eb3bfa640d <unknown>\n#6 0x55eb3bfcc14f <unknown>\n#7 0x55eb3bfa61b3 <unknown>\n#8 0x55eb3bf7259b <unknown>\n#9 0x55eb3bf73971 <unknown>\n#10 0x55eb3c4541fb <unknown>\n#11 0x55eb3c457f49 <unknown>\n#12 0x55eb3c43b2d9 <unknown>\n#13 0x55eb3c458af8 <unknown>\n#14 0x55eb3c41fbbf <unknown>\n#15 0x55eb3c47c0b8 <unknown>\n#16 0x55eb3c47c296 <unknown>\n#17 0x55eb3c48e006 <unknown>\n#18 0x7fbe0b29caa4 <unknown>\n#19 0x7fbe0b329c3c <unknown>\n",
      "timestamp": "2025-08-20T19:33:46.657660"
    },
    "CSELK-HNBF.R0001": {
      "rsi_data": null,
      "status": "failed",
      "error": "Error: Message: \nStacktrace:\n#0 0x559c2f14502a <unknown>\n#1 0x559c2ebe4a70 <unknown>\n#2 0x559c2ec36907 <unknown>\n#3 0x559c2ec36b01 <unknown>\n#4 0x559c2ec84d54 <unknown>\n#5 0x559c2ec5c40d <unknown>\n#6 0x559c2ec8214f <unknown>\n#7 0x559c2ec5c1b3 <unknown>\n#8 0x559c2ec2859b <unknown>\n#9 0x559c2ec29971 <unknown>\n#10 0x559c2f10a1fb <unknown>\n#11 0x559c2f10df49 <unknown>\n#12 0x559c2f0f12d9 <unknown>\n#13 0x559c2f10eaf8 <unknown>\n#14 0x559c2f0d5bbf <unknown>\n#15 0x559c2f1320b8 <unknown>\n#16 0x559c2f132296 <unknown>\n#17 0x559c2f144006 <unknown>\n#18 0x7f9c0b09caa4 <unknown>\n#19 0x7f9c0b129c3c <unknown>\n",
      "timestamp": "2025-08-20T19:33:54.311249"
    },
    "CSELK-HNBF.X0000": {
      "rsi_data": {
        "1D": 80.7,
        "1W": 84.4,
        "1M": 73.3
      },
      "status": "success",
      "successful_timeframes": 3,
      "timestamp": "2025-08-20T19:33:57.606607"
    },
    "CSELK-HOPL.N0000": {
      "rsi_data": {
        "1D": 49.3,
        "1W": 62.0,
        "1M": 61.7
      },
      "status": "success",
      "successful_timeframes": 3,
      "timestamp": "2025-08-20T19:34:05.363972"
    },
    "CSELK-HPFL.N0000": {
      "rsi_data": {
        "1D": 61.5,
        "1W": 61.8,
        "1M": 70.4
      },
      "status": "success",
      "successful_timeframes": 3,
      "timestamp": "2025-08-20T19:34:09.662398"
    },
    "CSELK-HPL.N0000": {
      "rsi_data": {
        "1D": 40.5,
        "1W": 47.3,
        "1M": 53.9
      },
      "status": "success",
      "successful_timeframes": 3,
      "timestamp": "2025-08-20T19:34:16.220419"
    },
    "CSELK-HSIG.N0000": {
      "rsi_data": {
        "1D": 67.2,
        "1W": 63.7,
        "1M": 68.2
      },
      "status": "success",
      "successful_timeframes": 3,
      "timestamp": "2025-08-20T19:34:20.554996"
    },
    "CSELK-HUNA.N0000": {
      "rsi_data": {
        "1D": 49.5,
        "1W": 38.4,
        "1M": 41.0
      },
      "status": "success",
      "successful_timeframes": 3,
      "timestamp": "2025-08-20T19:34:27.107314"
    },
    "CSELK-HUNT.N0000": {
      "rsi_data": {
        "1D": 54.4,
        "1W": 60.1,
        "1M": 64.88
      },
      "status": "success",
      "successful_timeframes": 3,
      "timestamp": "2025-08-20T19:34:31.689740"
    },
    "CSELK-HVA.N0000": {
      "rsi_data": {
        "1D": 50.0,
        "1W": 46.3,
        "1M": 46.4
      },
      "status": "success",
      "successful_timeframes": 3,
      "timestamp": "2025-08-20T19:34:37.973103"
    },
    "CSELK-JAT.N0000": {
      "rsi_data": {
        "1D": 48.1,
        "1W": 67.0,
        "1M": 75.2
      },
      "status": "success",
      "successful_timeframes": 3,
      "timestamp": "2025-08-20T19:34:42.592941"
    },
    "CSELK-JETS.N0000": {
      "rsi_data": {
        "1D": 75.8,
        "1W": 74.2,
        "1M": 72.4
      },
      "status": "success",
      "successful_timeframes": 3,
      "timestamp": "2025-08-20T19:34:48.908113"
    },
    "CSELK-JINS.N0000": {
      "rsi_data": {
        "1D": 74.6,
        "1W": 72.7,
        "1M": 77.3
      },
      "status": "success",
      "successful_timeframes": 3,
      "timestamp": "2025-08-20T19:34:54.527917"
    },
    "CSELK-JKH.N0000": {
      "rsi_data": {
        "1D": 51.8,
        "1W": 58.6,
        "1M": 65.0
      },
      "status": "success",
      "successful_timeframes": 3,
      "timestamp": "2025-08-20T19:34:59.888999"
    },
    "CSELK-JKL.N0000": {
      "rsi_data": {
        "1D": 42.3,
        "1W": 54.0,
        "1M": 61.5
      },
      "status": "success",
      "successful_timeframes": 3,
      "timestamp": "2025-08-20T19:35:05.512141"
    },
    "CSELK-KAHA.N0000": {
      "rsi_data": {
        "1D": 51.0,
        "1W": 50.5,
        "1M": 52.4
      },
      "status": "success",
      "successful_timeframes": 3,
      "timestamp": "2025-08-20T19:35:10.906055"
    },
    "CSELK-KCAB.N0000": {
      "rsi_data": {
        "1D": 74.98,
        "1W": 79.47,
        "1M": 78.37
      },
      "status": "success",
      "successful_timeframes": 3,
      "timestamp": "2025-08-20T19:35:16.519903"
    },
    "CSELK-KDL.N0000": {
      "rsi_data": {
        "1D": 46.2,
        "1W": 46.6,
        "1M": 45.7
      },
      "status": "success",
      "successful_timeframes": 3,
      "timestamp": "2025-08-20T19:35:21.804705"
    },
    "CSELK-KFP.N0000": {
      "rsi_data": {
        "1D": 54.1,
        "1W": 55.49,
        "1M": 57.19
      },
      "status": "success",
      "successful_timeframes": 3,
      "timestamp": "2025-08-20T19:35:27.584634"
    },
    "CSELK-KGAL.N0000": {
      "rsi_data": {
        "1D": 45.96,
        "1W": 47.76,
        "1M": 52.68
      },
      "status": "success",
      "successful_timeframes": 3,
      "timestamp": "2025-08-20T19:35:32.763905"
    },
    "CSELK-KHL.N0000": {
      "rsi_data": {
        "1D": 60.8,
        "1W": 59.6,
        "1M": 59.3
      },
      "status": "success",
      "successful_timeframes": 3,
      "timestamp": "2025-08-20T19:35:38.557754"
    },
    "CSELK-KOTA.N0000": {
      "rsi_data": {
        "1D": 48.8,
        "1W": 49.7,
        "1M": 59.5
      },
      "status": "success",
      "successful_timeframes": 3,
      "timestamp": "2025-08-20T19:35:47.068807"
    },
    "CSELK-KPHL.N0000": {
      "rsi_data": {
        "1D": 50.4,
        "1W": 50.0,
        "1M": 42.1
      },
      "status": "success",
      "successful_timeframes": 3,
      "timestamp": "2025-08-20T19:35:49.571542"
    },
    "CSELK-KVAL.N0000": {
      "rsi_data": {
        "1D": 50.7,
        "1W": 58.8,
        "1M": 58.4
      },
      "status": "success",
      "successful_timeframes": 3,
      "timestamp": "2025-08-20T19:35:57.991372"
    },
    "CSELK-LALU.N0000": {
      "rsi_data": {
        "1D": 56.7,
        "1W": 75.3,
        "1M": 74.8
      },
      "status": "success",
      "successful_timeframes": 3,
      "timestamp": "2025-08-20T19:36:00.540832"
    },
    "CSELK-LAMB.N0000": {
      "rsi_data": {
        "1D": 68.39,
        "1W": 75.78,
        "1M": 74.55
      },
      "status": "success",
      "successful_timeframes": 3,
      "timestamp": "2025-08-20T19:36:08.821260"
    },
    "CSELK-LCBF.N0000": {
      "rsi_data": {
        "1D": 68.0,
        "1W": 76.8,
        "1M": 75.5
      },
      "status": "success",
      "successful_timeframes": 3,
      "timestamp": "2025-08-20T19:36:11.490182"
    },
    "CSELK-LCEY.N0000": {
      "rsi_data": {
        "1D": 54.3,
        "1W": 53.1,
        "1M": 57.2
      },
      "status": "success",
      "successful_timeframes": 3,
      "timestamp": "2025-08-20T19:36:19.620918"
    },
    "CSELK-LDEV.N0000": {
      "rsi_data": {
        "1D": 52.1,
        "1W": 62.2,
        "1M": 61.8
      },
      "status": "success",
      "successful_timeframes": 3,
      "timestamp": "2025-08-20T19:36:22.302379"
    },
    "CSELK-LFIN.N0000": {
      "rsi_data": {
        "1D": 67.28,
        "1W": 83.04,
        "1M": 85.09
      },
      "status": "success",
      "successful_timeframes": 3,
      "timestamp": "2025-08-20T19:36:30.882086"
    },
    "CSELK-LGIL.N0000": {
      "rsi_data": {
        "1D": 48.6,
        "1W": 55.9,
        "1M": 50.6
      },
      "status": "success",
      "successful_timeframes": 3,
      "timestamp": "2025-08-20T19:36:33.264796"
    },
    "CSELK-LGL.N0000": {
      "rsi_data": {
        "1D": 60.0,
        "1W": 60.0,
        "1M": 54.1
      },
      "status": "success",
      "successful_timeframes": 3,
      "timestamp": "2025-08-20T19:36:42.006112"
    },
    "CSELK-LGL.X0000": {
      "rsi_data": {
        "1D": 61.8,
        "1W": 67.2,
        "1M": 59.1
      },
      "status": "success",
      "successful_timeframes": 3,
      "timestamp": "2025-08-20T19:36:44.075438"
    },
    "CSELK-LIOC.N0000": {
      "rsi_data": {
        "1D": 47.17,
        "1W": 53.5,
        "1M": 55.08
      },
      "status": "success",
      "successful_timeframes": 3,
      "timestamp": "2025-08-20T19:36:52.970829"
    },
    "CSELK-LION.N0000": {
      "rsi_data": {
        "1D": 49.36,
        "1W": 58.57,
        "1M": 74.37
      },
      "status": "success",
      "successful_timeframes": 3,
      "timestamp": "2025-08-20T19:36:55.025919"
    },
    "CSELK-LITE.N0000": {
      "rsi_data": {
        "1D": 67.9,
        "1W": 70.6,
        "1M": 87.6
      },
      "status": "success",
      "successful_timeframes": 3,
      "timestamp": "2025-08-20T19:37:03.880892"
    },
    "CSELK-LMF.N0000": {
      "rsi_data": {
        "1D": 54.9,
        "1W": 63.7,
        "1M": 76.9
      },
      "status": "success",
      "successful_timeframes": 3,
      "timestamp": "2025-08-20T19:37:05.944444"
    },
    "CSELK-LOFC.N0000": {
      "rsi_data": {
        "1D": 40.4,
        "1W": 44.1,
        "1M": 48.0
      },
      "status": "success",
      "successful_timeframes": 3,
      "timestamp": "2025-08-20T19:37:14.784797"
    },
    "CSELK-LOLC.N0000": {
      "rsi_data": {
        "1D": 47.97,
        "1W": 46.36,
        "1M": 53.55
      },
      "status": "success",
      "successful_timeframes": 3,
      "timestamp": "2025-08-20T19:37:16.825481"
    },
    "CSELK-LPL.N0000": {
      "rsi_data": {
        "1D": 50.4,
        "1W": 51.4,
        "1M": 56.9
      },
      "status": "success",
      "successful_timeframes": 3,
      "timestamp": "2025-08-20T19:37:25.763255"
    },
    "CSELK-LPL.X0000": {
      "rsi_data": {
        "1D": 49.4,
        "1W": 51.2,
        "1M": 54.3
      },
      "status": "success",
      "successful_timeframes": 3,
      "timestamp": "2025-08-20T19:37:27.667664"
    },
    "CSELK-LPRT.N0000": {
      "rsi_data": {
        "1D": 49.37,
        "1W": 54.0,
        "1M": 60.83
      },
      "status": "success",
      "successful_timeframes": 3,
      "timestamp": "2025-08-20T19:37:36.731230"
    },
    "CSELK-LUMX.N0000": {
      "rsi_data": {
        "1D": 45.8,
        "1W": 50.3,
        "1M": 46.6
      },
      "status": "success",
      "successful_timeframes": 3,
      "timestamp": "2025-08-20T19:37:38.591565"
    },
    "CSELK-LVEF.N0000": {
      "rsi_data": {
        "1D": 78.0,
        "1W": 80.8,
        "1M": 76.5
      },
      "status": "success",
      "successful_timeframes": 3,
      "timestamp": "2025-08-20T19:37:47.673679"
    },
    "CSELK-LVEN.N0000": {
      "rsi_data": {
        "1D": 73.9,
        "1W": 83.9,
        "1M": 82.2
      },
      "status": "success",
      "successful_timeframes": 3,
      "timestamp": "2025-08-20T19:37:49.487398"
    },
    "CSELK-LWL.N0000": {
      "rsi_data": {
        "1D": 46.7,
        "1W": 46.5,
        "1M": 48.8
      },
      "status": "success",
      "successful_timeframes": 3,
      "timestamp": "2025-08-20T19:37:58.607142"
    },
    "CSELK-MADU.N0000": {
      "rsi_data": {
        "1D": 54.8,
        "1W": 50.6,
        "1M": 53.1
      },
      "status": "success",
      "successful_timeframes": 3,
      "timestamp": "2025-08-20T19:38:00.430380"
    },
    "CSELK-MAL.N0000": {
      "rsi_data": {
        "1D": 54.9,
        "1W": 55.1,
        "1M": 54.6
      },
      "status": "success",
      "successful_timeframes": 3,
      "timestamp": "2025-08-20T19:38:09.852125"
    },
    "CSELK-MAL.X0000": {
      "rsi_data": {
        "1D": 56.2,
        "1W": 59.6,
        "1M": 57.6
      },
      "status": "success",
      "successful_timeframes": 3,
      "timestamp": "2025-08-20T19:38:11.499175"
    },
    "CSELK-MASK.N0000": {
      "rsi_data": {
        "1D": 47.3,
        "1W": 56.3,
        "1M": 67.2
      },
      "status": "success",
      "successful_timeframes": 3,
      "timestamp": "2025-08-20T19:38:22.345980"
    },
    "CSELK-MBSL.N0000": {
      "rsi_data": {
        "1D": 73.5,
        "1W": 70.1,
        "1M": 68.0
      },
      "status": "success",
      "successful_timeframes": 3,
      "timestamp": "2025-08-20T19:38:33.236386"
    },
    "CSELK-MAWA.N0000": {
      "rsi_data": null,
      "status": "failed",
      "error": "Error: Message: \nStacktrace:\n#0 0x5621bac4d02a <unknown>\n#1 0x5621ba6eca70 <unknown>\n#2 0x5621ba73e907 <unknown>\n#3 0x5621ba73eb01 <unknown>\n#4 0x5621ba78cd54 <unknown>\n#5 0x5621ba76440d <unknown>\n#6 0x5621ba78a14f <unknown>\n#7 0x5621ba7641b3 <unknown>\n#8 0x5621ba73059b <unknown>\n#9 0x5621ba731971 <unknown>\n#10 0x5621bac121fb <unknown>\n#11 0x5621bac15f49 <unknown>\n#12 0x5621babf92d9 <unknown>\n#13 0x5621bac16af8 <unknown>\n#14 0x5621babddbbf <unknown>\n#15 0x5621bac3a0b8 <unknown>\n#16 0x5621bac3a296 <unknown>\n#17 0x5621bac4c006 <unknown>\n#18 0x7f98f729caa4 <unknown>\n#19 0x7f98f7329c3c <unknown>\n",
      "timestamp": "2025-08-20T19:38:35.732037"
    },
    "CSELK-MCPL.N0000": {
      "rsi_data": {
        "1D": 65.3,
        "1W": 73.4,
        "1M": 66.2
      },
      "status": "success",
      "successful_timeframes": 3,
      "timestamp": "2025-08-20T19:38:44.169496"
    },
    "CSELK-MDL.N0000": {
      "rsi_data": {
        "1D": 51.7,
        "1W": 57.2,
        "1M": 47.4
      },
      "status": "success",
      "successful_timeframes": 3,
      "timestamp": "2025-08-20T19:38:46.580478"
    },
    "CSELK-MEL.N0000": {
      "rsi_data": {
        "1D": 55.9,
        "1W": 64.9,
        "1M": 67.4
      },
      "status": "success",
      "successful_timeframes": 3,
      "timestamp": "2025-08-20T19:38:55.092540"
    },
    "CSELK-MELS.N0000": {
      "rsi_data": {
        "1D": 69.69,
        "1W": 78.39,
        "1M": 80.52
      },
      "status": "success",
      "successful_timeframes": 3,
      "timestamp": "2025-08-20T19:38:57.486901"
    },
    "CSELK-MFPE.N0000": {
      "rsi_data": {
        "1D": 51.7,
        "1W": 66.7,
        "1M": null
      },
      "status": "success",
      "successful_timeframes": 2,
      "timestamp": "2025-08-20T19:39:13.413094"
    },
    "CSELK-MERC.N0000": {
      "rsi_data": null,
      "status": "failed",
      "error": "Error: Message: \nStacktrace:\n#0 0x55631ba0902a <unknown>\n#1 0x55631b4a8a70 <unknown>\n#2 0x55631b4fa907 <unknown>\n#3 0x55631b4fab01 <unknown>\n#4 0x55631b548d54 <unknown>\n#5 0x55631b52040d <unknown>\n#6 0x55631b54614f <unknown>\n#7 0x55631b5201b3 <unknown>\n#8 0x55631b4ec59b <unknown>\n#9 0x55631b4ed971 <unknown>\n#10 0x55631b9ce1fb <unknown>\n#11 0x55631b9d1f49 <unknown>\n#12 0x55631b9b52d9 <unknown>\n#13 0x55631b9d2af8 <unknown>\n#14 0x55631b999bbf <unknown>\n#15 0x55631b9f60b8 <unknown>\n#16 0x55631b9f6296 <unknown>\n#17 0x55631ba08006 <unknown>\n#18 0x7fb98929caa4 <unknown>\n#19 0x7fb989329c3c <unknown>\n",
      "timestamp": "2025-08-20T19:39:20.925568"
    },
    "CSELK-MGT.N0000": {
      "rsi_data": {
        "1D": 45.6,
        "1W": 46.5,
        "1M": 51.7
      },
      "status": "success",
      "successful_timeframes": 3,
      "timestamp": "2025-08-20T19:39:24.748390"
    },
    "CSELK-MHDL.N0000": {
      "rsi_data": {
        "1D": 51.0,
        "1W": 65.4,
        "1M": 75.1
      },
      "status": "success",
      "successful_timeframes": 3,
      "timestamp": "2025-08-20T19:39:31.907372"
    },
    "CSELK-MRH.N0000": {
      "rsi_data": {
        "1D": 50.5,
        "1W": 54.0,
        "1M": 64.2
      },
      "status": "success",
      "successful_timeframes": 3,
      "timestamp": "2025-08-20T19:39:35.603996"
    },
    "CSELK-MSL.N0000": {
      "rsi_data": {
        "1D": 44.92,
        "1W": 53.95,
        "1M": 60.28
      },
      "status": "success",
      "successful_timeframes": 3,
      "timestamp": "2025-08-20T19:39:42.784989"
    },
    "CSELK-MULL.N0000": {
      "rsi_data": {
        "1D": 49.0,
        "1W": 62.3,
        "1M": 62.5
      },
      "status": "success",
      "successful_timeframes": 3,
      "timestamp": "2025-08-20T19:39:46.459587"
    },
    "CSELK-NAMU.N0000": {
      "rsi_data": {
        "1D": 65.52,
        "1W": 68.23,
        "1M": 66.17
      },
      "status": "success",
      "successful_timeframes": 3,
      "timestamp": "2025-08-20T19:39:53.719306"
    },
    "CSELK-NDB.N0000": {
      "rsi_data": {
        "1D": 72.73,
        "1W": 76.76,
        "1M": 75.55
      },
      "status": "success",
      "successful_timeframes": 3,
      "timestamp": "2025-08-20T19:40:04.707090"
    },
    "CSELK-NAVF.U0000": {
      "rsi_data": {
        "1D": 53.4,
        "1W": 53.2,
        "1M": null
      },
      "status": "success",
      "successful_timeframes": 2,
      "timestamp": "2025-08-20T19:40:13.567699"
    },
    "CSELK-NHL.N0000": {
      "rsi_data": {
        "1D": 68.8,
        "1W": 81.1,
        "1M": 70.0
      },
      "status": "success",
      "successful_timeframes": 3,
      "timestamp": "2025-08-20T19:40:15.524604"
    },
    "CSELK-NTB.N0000": {
      "rsi_data": {
        "1D": 89.95,
        "1W": 81.97,
        "1M": 87.25
      },
      "status": "success",
      "successful_timeframes": 3,
      "timestamp": "2025-08-20T19:40:24.540973"
    },
    "CSELK-NTB.X0000": {
      "rsi_data": {
        "1D": 57.01,
        "1W": 60.12,
        "1M": 70.16
      },
      "status": "success",
      "successful_timeframes": 3,
      "timestamp": "2025-08-20T19:40:26.425847"
    },
    "CSELK-PACK.N0000": {
      "rsi_data": {
        "1D": 50.9,
        "1W": 54.2,
        "1M": 49.8
      },
      "status": "success",
      "successful_timeframes": 3,
      "timestamp": "2025-08-20T19:40:35.489570"
    },
    "CSELK-SHAW.N0000": {
      "rsi_data": {
        "1D": 55.88,
        "1W": 71.18,
        "1M": 80.46
      },
      "status": "success",
      "successful_timeframes": 3,
      "timestamp": "2025-08-20T19:40:37.324779"
    },
    "CSELK-TILE.N0000": {
      "rsi_data": {
        "1D": 41.0,
        "1W": 45.3,
        "1M": 50.7
      },
      "status": "success",
      "successful_timeframes": 3,
      "timestamp": "2025-08-20T19:40:46.362356"
    },
    "CSELK-TYRE.N0000": {
      "rsi_data": {
        "1D": 61.03,
        "1W": 84.15,
        "1M": 74.93
      },
      "status": "success",
      "successful_timeframes": 3,
      "timestamp": "2025-08-20T19:40:48.274827"
    },
    "CSELK-WAPO.N0000": {
      "rsi_data": {
        "1D": 79.3,
        "1W": 79.3,
        "1M": 79.3
      },
      "status": "success",
      "successful_timeframes": 3,
      "timestamp": "2025-08-20T19:40:57.315372"
    },
    "CSELK-AAIC.N0000": {
      "rsi_data": {
        "1D": 61.3,
        "1W": 66.7,
        "1M": 59.2
      },
      "status": "success",
      "successful_timeframes": 3,
      "timestamp": "2025-08-20T19:40:59.310265"
    },
    "CSELK-AUTO.N0000": {
      "rsi_data": {
        "1D": 81.46,
        "1W": 71.93,
        "1M": 64.26
      },
      "status": "success",
      "successful_timeframes": 3,
      "timestamp": "2025-08-20T19:41:08.215020"
    },
    "CSELK-CARE.N0000": {
      "rsi_data": {
        "1D": 44.4,
        "1W": 45.6,
        "1M": 53.4
      },
      "status": "success",
      "successful_timeframes": 3,
      "timestamp": "2025-08-20T19:41:10.326822"
    },
    "CSELK-COCO.N0000": {
      "rsi_data": {
        "1D": 59.1,
        "1W": 63.9,
        "1M": 55.4
      },
      "status": "success",
      "successful_timeframes": 3,
      "timestamp": "2025-08-20T19:41:21.320982"
    },
    "CSELK-CFLB.N0000": {
      "rsi_data": {
        "1D": 65.0,
        "1W": 77.6,
        "1M": 81.5
      },
      "status": "success",
      "successful_timeframes": 3,
      "timestamp": "2025-08-20T19:41:25.330156"
    },
    "CSELK-COCO.X0000": {
      "rsi_data": {
        "1D": 62.1,
        "1W": 70.1,
        "1M": 57.8
      },
      "status": "success",
      "successful_timeframes": 3,
      "timestamp": "2025-08-20T19:41:32.251977"
    },
    "CSELK-COF.U0000": {
      "rsi_data": {
        "1D": 55.2,
        "1W": 54.2,
        "1M": 50.7
      },
      "status": "success",
      "successful_timeframes": 3,
      "timestamp": "2025-08-20T19:41:36.746778"
    },
    "CSELK-CRL.N0000": {
      "rsi_data": {
        "1D": 54.1,
        "1W": 54.0,
        "1M": 45.1
      },
      "status": "success",
      "successful_timeframes": 3,
      "timestamp": "2025-08-20T19:41:43.179567"
    },
    "CSELK-CSD.N0000": {
      "rsi_data": {
        "1D": 50.2,
        "1W": 64.0,
        "1M": 72.5
      },
      "status": "success",
      "successful_timeframes": 3,
      "timestamp": "2025-08-20T19:41:47.674563"
    },
    "CSELK-GLAS.N0000": {
      "rsi_data": {
        "1D": 55.6,
        "1W": 76.0,
        "1M": 89.5
      },
      "status": "success",
      "successful_timeframes": 3,
      "timestamp": "2025-08-20T19:41:54.007661"
    },
    "CSELK-HPWR.N0000": {
      "rsi_data": {
        "1D": 72.4,
        "1W": 72.2,
        "1M": 71.6
      },
      "status": "success",
      "successful_timeframes": 3,
      "timestamp": "2025-08-20T19:41:58.634969"
    },
    "CSELK-IDL.N0000": {
      "rsi_data": {
        "1D": 29.3,
        "1W": 28.3,
        "1M": 36.3
      },
      "status": "success",
      "successful_timeframes": 3,
      "timestamp": "2025-08-20T19:42:05.071703"
    },
    "CSELK-KHC.N0000": {
      "rsi_data": {
        "1D": 76.8,
        "1W": 76.4,
        "1M": 73.2
      },
      "status": "success",
      "successful_timeframes": 3,
      "timestamp": "2025-08-20T19:42:09.683165"
    },
    "CSELK-LHCL.N0000": {
      "rsi_data": {
        "1D": 55.7,
        "1W": 58.2,
        "1M": 48.3
      },
      "status": "success",
      "successful_timeframes": 3,
      "timestamp": "2025-08-20T19:42:15.945058"
    },
    "CSELK-LHL.N0000": {
      "rsi_data": {
        "1D": 54.9,
        "1W": 69.1,
        "1M": 82.3
      },
      "status": "success",
      "successful_timeframes": 3,
      "timestamp": "2025-08-20T19:42:20.496754"
    },
    "CSELK-NEH.N0000": {
      "rsi_data": {
        "1D": 65.45,
        "1W": 86.52,
        "1M": 79.98
      },
      "status": "success",
      "successful_timeframes": 3,
      "timestamp": "2025-08-20T19:42:26.846076"
    },
    "CSELK-ODEL.N0000": {
      "rsi_data": {
        "1D": 51.3,
        "1W": 53.7,
        "1M": 42.8
      },
      "status": "success",
      "successful_timeframes": 3,
      "timestamp": "2025-08-20T19:42:31.445556"
    },
    "CSELK-OFEQ.N0000": {
      "rsi_data": {
        "1D": 63.69,
        "1W": 57.16,
        "1M": 60.35
      },
      "status": "success",
      "successful_timeframes": 3,
      "timestamp": "2025-08-20T19:42:37.790769"
    },
    "CSELK-ONAL.N0000": {
      "rsi_data": {
        "1D": 51.9,
        "1W": 65.3,
        "1M": 64.4
      },
      "status": "success",
      "successful_timeframes": 3,
      "timestamp": "2025-08-20T19:42:42.335070"
    },
    "CSELK-OSEA.N0000": {
      "rsi_data": {
        "1D": 67.3,
        "1W": 81.9,
        "1M": 85.2
      },
      "status": "success",
      "successful_timeframes": 3,
      "timestamp": "2025-08-20T19:42:48.796876"
    },
    "CSELK-PABC.N0000": {
      "rsi_data": {
        "1D": 72.5,
        "1W": 87.0,
        "1M": 84.7
      },
      "status": "success",
      "successful_timeframes": 3,
      "timestamp": "2025-08-20T19:42:53.124861"
    },
    "CSELK-PALM.N0000": {
      "rsi_data": {
        "1D": 52.1,
        "1W": 54.6,
        "1M": 61.5
      },
      "status": "success",
      "successful_timeframes": 3,
      "timestamp": "2025-08-20T19:42:59.811964"
    },
    "CSELK-PAP.N0000": {
      "rsi_data": {
        "1D": 59.6,
        "1W": 70.2,
        "1M": 88.1
      },
      "status": "success",
      "successful_timeframes": 3,
      "timestamp": "2025-08-20T19:43:04.013796"
    },
    "CSELK-PARA.N0000": {
      "rsi_data": {
        "1D": 53.9,
        "1W": 57.5,
        "1M": 64.5
      },
      "status": "success",
      "successful_timeframes": 3,
      "timestamp": "2025-08-20T19:43:10.754174"
    },
    "CSELK-PARQ.N0000": {
      "rsi_data": {
        "1D": 47.4,
        "1W": 70.7,
        "1M": 82.3
      },
      "status": "success",
      "successful_timeframes": 3,
      "timestamp": "2025-08-20T19:43:14.876016"
    },
    "CSELK-PEG.N0000": {
      "rsi_data": {
        "1D": 51.2,
        "1W": 56.0,
        "1M": 58.9
      },
      "status": "success",
      "successful_timeframes": 3,
      "timestamp": "2025-08-20T19:43:21.761634"
    },
    "CSELK-PINS.N0000": {
      "rsi_data": {
        "1D": 55.1,
        "1W": 68.3,
        "1M": 70.2
      },
      "status": "success",
      "successful_timeframes": 3,
      "timestamp": "2025-08-20T19:43:25.930394"
    },
    "CSELK-PLC.N0000": {
      "rsi_data": {
        "1D": 54.4,
        "1W": 69.2,
        "1M": 77.9
      },
      "status": "success",
      "successful_timeframes": 3,
      "timestamp": "2025-08-20T19:43:32.629355"
    },
    "CSELK-PLR.N0000": {
      "rsi_data": {
        "1D": 69.1,
        "1W": 79.2,
        "1M": 81.6
      },
      "status": "success",
      "successful_timeframes": 3,
      "timestamp": "2025-08-20T19:43:36.847862"
    },
    "CSELK-PMB.N0000": {
      "rsi_data": {
        "1D": 78.1,
        "1W": 80.7,
        "1M": 85.3
      },
      "status": "success",
      "successful_timeframes": 3,
      "timestamp": "2025-08-20T19:43:43.522101"
    },
    "CSELK-RAL.N0000": {
      "rsi_data": {
        "1D": 54.8,
        "1W": 58.6,
        "1M": 53.4
      },
      "status": "success",
      "successful_timeframes": 3,
      "timestamp": "2025-08-20T19:43:47.681376"
    },
    "CSELK-RCH.N0000": {
      "rsi_data": {
        "1D": 59.71,
        "1W": 75.48,
        "1M": 78.94
      },
      "status": "success",
      "successful_timeframes": 3,
      "timestamp": "2025-08-20T19:43:54.449491"
    },
    "CSELK-RCL.N0000": {
      "rsi_data": {
        "1D": 52.8,
        "1W": 63.2,
        "1M": 59.6
      },
      "status": "success",
      "successful_timeframes": 3,
      "timestamp": "2025-08-20T19:43:58.618154"
    },
    "CSELK-RENU.N0000": {
      "rsi_data": {
        "1D": 59.29,
        "1W": 75.24,
        "1M": 80.84
      },
      "status": "success",
      "successful_timeframes": 3,
      "timestamp": "2025-08-20T19:44:05.515402"
    },
    "CSELK-REXP.N0000": {
      "rsi_data": {
        "1D": 53.22,
        "1W": 50.02,
        "1M": 39.67
      },
      "status": "success",
      "successful_timeframes": 3,
      "timestamp": "2025-08-20T19:44:09.449787"
    },
    "CSELK-RFL.N0000": {
      "rsi_data": {
        "1D": 55.0,
        "1W": 56.9,
        "1M": 62.9
      },
      "status": "success",
      "successful_timeframes": 3,
      "timestamp": "2025-08-20T19:44:16.834273"
    },
    "CSELK-RGEM.N0000": {
      "rsi_data": {
        "1D": 70.6,
        "1W": 61.7,
        "1M": 55.8
      },
      "status": "success",
      "successful_timeframes": 3,
      "timestamp": "2025-08-20T19:44:20.573464"
    },
    "CSELK-RHL.N0000": {
      "rsi_data": {
        "1D": 74.8,
        "1W": 79.5,
        "1M": 72.5
      },
      "status": "success",
      "successful_timeframes": 3,
      "timestamp": "2025-08-20T19:44:27.824908"
    },
    "CSELK-RHL.X0000": {
      "rsi_data": {
        "1D": 75.6,
        "1W": 82.0,
        "1M": 76.0
      },
      "status": "success",
      "successful_timeframes": 3,
      "timestamp": "2025-08-20T19:44:31.466764"
    },
    "CSELK-RHTL.N0000": {
      "rsi_data": {
        "1D": 57.8,
        "1W": 62.7,
        "1M": 62.6
      },
      "status": "success",
      "successful_timeframes": 3,
      "timestamp": "2025-08-20T19:44:38.664146"
    },
    "CSELK-RICH.N0000": {
      "rsi_data": {
        "1D": 55.1,
        "1W": 58.2,
        "1M": 59.2
      },
      "status": "success",
      "successful_timeframes": 3,
      "timestamp": "2025-08-20T19:44:42.389138"
    },
    "CSELK-RIL.N0000": {
      "rsi_data": {
        "1D": 47.2,
        "1W": 71.3,
        "1M": 80.4
      },
      "status": "success",
      "successful_timeframes": 3,
      "timestamp": "2025-08-20T19:44:49.451740"
    },
    "CSELK-RPBH.N0000": {
      "rsi_data": {
        "1D": 69.6,
        "1W": 88.3,
        "1M": 83.2
      },
      "status": "success",
      "successful_timeframes": 3,
      "timestamp": "2025-08-20T19:44:53.258918"
    },
    "CSELK-RWSL.N0000": {
      "rsi_data": {
        "1D": 79.2,
        "1W": 78.0,
        "1M": 83.3
      },
      "status": "success",
      "successful_timeframes": 3,
      "timestamp": "2025-08-20T19:45:01.303013"
    },
    "CSELK-SAMP.N0000": {
      "rsi_data": {
        "1D": 73.64,
        "1W": 79.38,
        "1M": 78.37
      },
      "status": "success",
      "successful_timeframes": 3,
      "timestamp": "2025-08-20T19:45:04.075995"
    },
    "CSELK-SCAP.N0000": {
      "rsi_data": {
        "1D": 54.7,
        "1W": 55.8,
        "1M": 46.5
      },
      "status": "success",
      "successful_timeframes": 3,
      "timestamp": "2025-08-20T19:45:12.159557"
    },
    "CSELK-SDB.N0000": {
      "rsi_data": {
        "1D": 73.1,
        "1W": 69.8,
        "1M": 65.2
      },
      "status": "success",
      "successful_timeframes": 3,
      "timestamp": "2025-08-20T19:45:14.977950"
    },
    "CSELK-SDF.N0000": {
      "rsi_data": {
        "1D": 51.6,
        "1W": 68.6,
        "1M": 75.8
      },
      "status": "success",
      "successful_timeframes": 3,
      "timestamp": "2025-08-20T19:45:23.100993"
    },
    "CSELK-SEMB.N0000": {
      "rsi_data": {
        "1D": 46.4,
        "1W": 49.6,
        "1M": 49.6
      },
      "status": "success",
      "successful_timeframes": 3,
      "timestamp": "2025-08-20T19:45:25.773291"
    },
    "CSELK-SEMB.X0000": {
      "rsi_data": {
        "1D": 58.1,
        "1W": 61.1,
        "1M": 58.4
      },
      "status": "success",
      "successful_timeframes": 3,
      "timestamp": "2025-08-20T19:45:33.980871"
    },
    "CSELK-SERV.N0000": {
      "rsi_data": {
        "1D": 71.7,
        "1W": 72.0,
        "1M": 71.8
      },
      "status": "success",
      "successful_timeframes": 3,
      "timestamp": "2025-08-20T19:45:36.678894"
    },
    "CSELK-SEYB.X0000": {
      "rsi_data": {
        "1D": 76.6,
        "1W": 79.5,
        "1M": 76.2
      },
      "status": "success",
      "successful_timeframes": 3,
      "timestamp": "2025-08-20T19:45:47.624691"
    },
    "CSELK-SEYB.N0000": {
      "rsi_data": {
        "1D": 80.5,
        "1W": 79.5,
        "1M": 78.0
      },
      "status": "success",
      "successful_timeframes": 3,
      "timestamp": "2025-08-20T19:45:47.921417"
    },
    "CSELK-SFCL.N0000": {
      "rsi_data": {
        "1D": 44.81,
        "1W": 52.86,
        "1M": 59.12
      },
      "status": "success",
      "successful_timeframes": 3,
      "timestamp": "2025-08-20T19:45:58.686322"
    },
    "CSELK-SFIN.N0000": {
      "rsi_data": {
        "1D": 86.3,
        "1W": 87.7,
        "1M": 91.2
      },
      "status": "success",
      "successful_timeframes": 3,
      "timestamp": "2025-08-20T19:45:59.092269"
    },
    "CSELK-SHL.N0000": {
      "rsi_data": {
        "1D": 41.5,
        "1W": 43.9,
        "1M": 41.2
      },
      "status": "success",
      "successful_timeframes": 3,
      "timestamp": "2025-08-20T19:46:09.715926"
    },
    "CSELK-SHOT.N0000": {
      "rsi_data": {
        "1D": 52.8,
        "1W": 54.4,
        "1M": 62.4
      },
      "status": "success",
      "successful_timeframes": 3,
      "timestamp": "2025-08-20T19:46:20.732418"
    },
    "CSELK-SHL.W0000": {
      "rsi_data": null,
      "status": "failed",
      "error": "Error: Message: \nStacktrace:\n#0 0x5582a67fe02a <unknown>\n#1 0x5582a629da70 <unknown>\n#2 0x5582a62ef907 <unknown>\n#3 0x5582a62efb01 <unknown>\n#4 0x5582a633dd54 <unknown>\n#5 0x5582a631540d <unknown>\n#6 0x5582a633b14f <unknown>\n#7 0x5582a63151b3 <unknown>\n#8 0x5582a62e159b <unknown>\n#9 0x5582a62e2971 <unknown>\n#10 0x5582a67c31fb <unknown>\n#11 0x5582a67c6f49 <unknown>\n#12 0x5582a67aa2d9 <unknown>\n#13 0x5582a67c7af8 <unknown>\n#14 0x5582a678ebbf <unknown>\n#15 0x5582a67eb0b8 <unknown>\n#16 0x5582a67eb296 <unknown>\n#17 0x5582a67fd006 <unknown>\n#18 0x7f3c2569caa4 <unknown>\n#19 0x7f3c25729c3c <unknown>\n",
      "timestamp": "2025-08-20T19:46:25.118019"
    },
    "CSELK-SHOT.X0000": {
      "rsi_data": {
        "1D": 54.7,
        "1W": 56.5,
        "1M": 63.9
      },
      "status": "success",
      "successful_timeframes": 3,
      "timestamp": "2025-08-20T19:46:31.827350"
    },
    "CSELK-SIGV.N0000": {
      "rsi_data": {
        "1D": 58.06,
        "1W": 65.4,
        "1M": 80.23
      },
      "status": "success",
      "successful_timeframes": 3,
      "timestamp": "2025-08-20T19:46:35.993858"
    },
    "CSELK-SIL.N0000": {
      "rsi_data": {
        "1D": 59.01,
        "1W": 60.07,
        "1M": 53.48
      },
      "status": "success",
      "successful_timeframes": 3,
      "timestamp": "2025-08-20T19:46:42.738893"
    },
    "CSELK-SING.N0000": {
      "rsi_data": {
        "1D": 77.2,
        "1W": 86.3,
        "1M": 69.3
      },
      "status": "success",
      "successful_timeframes": 3,
      "timestamp": "2025-08-20T19:46:50.530628"
    },
    "CSELK-SINH.N0000": {
      "rsi_data": {
        "1D": 58.1,
        "1W": 73.9,
        "1M": 85.9
      },
      "status": "success",
      "successful_timeframes": 3,
      "timestamp": "2025-08-20T19:46:53.542507"
    },
    "CSELK-SINS.N0000": {
      "rsi_data": {
        "1D": 69.0,
        "1W": 82.2,
        "1M": 89.1
      },
      "status": "success",
      "successful_timeframes": 3,
      "timestamp": "2025-08-20T19:47:01.445127"
    },
    "CSELK-SIRA.N0000": {
      "rsi_data": {
        "1D": 82.6,
        "1W": 79.8,
        "1M": 71.8
      },
      "status": "success",
      "successful_timeframes": 3,
      "timestamp": "2025-08-20T19:47:04.320854"
    },
    "CSELK-SLND.N0000": {
      "rsi_data": {
        "1D": 64.61,
        "1W": 72.2,
        "1M": 60.91
      },
      "status": "success",
      "successful_timeframes": 3,
      "timestamp": "2025-08-20T19:47:12.336313"
    },
    "CSELK-SLTL.N0000": {
      "rsi_data": {
        "1D": 65.8,
        "1W": 55.2,
        "1M": 44.9
      },
      "status": "success",
      "successful_timeframes": 3,
      "timestamp": "2025-08-20T19:47:15.271127"
    },
    "CSELK-SMOT.N0000": {
      "rsi_data": {
        "1D": 48.35,
        "1W": 72.7,
        "1M": 79.04
      },
      "status": "success",
      "successful_timeframes": 3,
      "timestamp": "2025-08-20T19:47:23.153077"
    },
    "CSELK-SUN.N0000": {
      "rsi_data": {
        "1D": 49.7,
        "1W": 67.5,
        "1M": 75.1
      },
      "status": "success",
      "successful_timeframes": 3,
      "timestamp": "2025-08-20T19:47:26.151389"
    },
    "CSELK-SWAD.N0000": {
      "rsi_data": {
        "1D": 68.03,
        "1W": 64.63,
        "1M": 61.26
      },
      "status": "success",
      "successful_timeframes": 3,
      "timestamp": "2025-08-20T19:47:34.237130"
    },
    "CSELK-TAFL.N0000": {
      "rsi_data": {
        "1D": 36.39,
        "1W": 65.06,
        "1M": 70.84
      },
      "status": "success",
      "successful_timeframes": 3,
      "timestamp": "2025-08-20T19:47:37.084225"
    },
    "CSELK-TAJ.N0000": {
      "rsi_data": {
        "1D": 71.0,
        "1W": 88.2,
        "1M": 81.9
      },
      "status": "success",
      "successful_timeframes": 3,
      "timestamp": "2025-08-20T19:47:45.198744"
    },
    "CSELK-TANG.N0000": {
      "rsi_data": {
        "1D": 62.92,
        "1W": 73.83,
        "1M": 78.71
      },
      "status": "success",
      "successful_timeframes": 3,
      "timestamp": "2025-08-20T19:47:47.982696"
    },
    "CSELK-TESS.N0000": {
      "rsi_data": {
        "1D": 45.1,
        "1W": 47.6,
        "1M": 50.2
      },
      "status": "success",
      "successful_timeframes": 3,
      "timestamp": "2025-08-20T19:47:56.130512"
    },
    "CSELK-TESS.X0000": {
      "rsi_data": {
        "1D": 46.9,
        "1W": 53.4,
        "1M": 55.9
      },
      "status": "success",
      "successful_timeframes": 3,
      "timestamp": "2025-08-20T19:47:58.803805"
    },
    "CSELK-TJL.N0000": {
      "rsi_data": {
        "1D": 32.0,
        "1W": 41.6,
        "1M": 52.9
      },
      "status": "success",
      "successful_timeframes": 3,
      "timestamp": "2025-08-20T19:48:07.038149"
    },
    "CSELK-TKYO.N0000": {
      "rsi_data": {
        "1D": 61.0,
        "1W": 61.5,
        "1M": 71.3
      },
      "status": "success",
      "successful_timeframes": 3,
      "timestamp": "2025-08-20T19:48:09.735280"
    },
    "CSELK-TKYO.X0000": {
      "rsi_data": {
        "1D": 64.7,
        "1W": 64.3,
        "1M": 71.3
      },
      "status": "success",
      "successful_timeframes": 3,
      "timestamp": "2025-08-20T19:48:18.256387"
    },
    "CSELK-TPL.N0000": {
      "rsi_data": {
        "1D": 55.62,
        "1W": 63.3,
        "1M": 66.37
      },
      "status": "success",
      "successful_timeframes": 3,
      "timestamp": "2025-08-20T19:48:20.739191"
    },
    "CSELK-TRAN.N0000": {
      "rsi_data": {
        "1D": 63.4,
        "1W": 72.8,
        "1M": 64.8
      },
      "status": "success",
      "successful_timeframes": 3,
      "timestamp": "2025-08-20T19:48:29.196824"
    },
    "CSELK-TSML.N0000": {
      "rsi_data": {
        "1D": 86.7,
        "1W": 84.0,
        "1M": 68.8
      },
      "status": "success",
      "successful_timeframes": 3,
      "timestamp": "2025-08-20T19:48:31.630639"
    },
    "CSELK-UAL.N0000": {
      "rsi_data": {
        "1D": 48.6,
        "1W": 60.2,
        "1M": 67.7
      },
      "status": "success",
      "successful_timeframes": 3,
      "timestamp": "2025-08-20T19:48:40.325404"
    },
    "CSELK-UBC.N0000": {
      "rsi_data": {
        "1D": 65.9,
        "1W": 69.9,
        "1M": 64.9
      },
      "status": "success",
      "successful_timeframes": 3,
      "timestamp": "2025-08-20T19:48:42.524346"
    },
    "CSELK-UBF.N0000": {
      "rsi_data": {
        "1D": 61.5,
        "1W": 76.7,
        "1M": 68.2
      },
      "status": "success",
      "successful_timeframes": 3,
      "timestamp": "2025-08-20T19:48:51.310787"
    },
    "CSELK-UCAR.N0000": {
      "rsi_data": {
        "1D": 68.45,
        "1W": 71.55,
        "1M": 67.98
      },
      "status": "success",
      "successful_timeframes": 3,
      "timestamp": "2025-08-20T19:48:53.426302"
    },
    "CSELK-UDPL.N0000": {
      "rsi_data": {
        "1D": 77.93,
        "1W": 66.68,
        "1M": 67.88
      },
      "status": "success",
      "successful_timeframes": 3,
      "timestamp": "2025-08-20T19:49:02.339765"
    },
    "CSELK-UML.N0000": {
      "rsi_data": {
        "1D": 51.09,
        "1W": 72.13,
        "1M": 76.99
      },
      "status": "success",
      "successful_timeframes": 3,
      "timestamp": "2025-08-20T19:49:04.342050"
    },
    "CSELK-VFIN.N0000": {
      "rsi_data": {
        "1D": 75.65,
        "1W": 84.48,
        "1M": 90.13
      },
      "status": "success",
      "successful_timeframes": 3,
      "timestamp": "2025-08-20T19:49:13.250412"
    },
    "CSELK-VLL.N0000": {
      "rsi_data": {
        "1D": 75.7,
        "1W": 74.4,
        "1M": 85.5
      },
      "status": "success",
      "successful_timeframes": 3,
      "timestamp": "2025-08-20T19:49:15.333628"
    },
    "CSELK-VLL.X0000": {
      "rsi_data": {
        "1D": 74.6,
        "1W": 90.8,
        "1M": 90.5
      },
      "status": "success",
      "successful_timeframes": 3,
      "timestamp": "2025-08-20T19:49:24.230738"
    },
    "CSELK-VONE.N0000": {
      "rsi_data": {
        "1D": 51.6,
        "1W": 78.8,
        "1M": 71.4
      },
      "status": "success",
      "successful_timeframes": 3,
      "timestamp": "2025-08-20T19:49:26.361293"
    },
    "CSELK-VPEL.N0000": {
      "rsi_data": {
        "1D": 47.5,
        "1W": 59.9,
        "1M": 72.6
      },
      "status": "success",
      "successful_timeframes": 3,
      "timestamp": "2025-08-20T19:49:35.194227"
    }
  }
}