{
  "metadata": {
    "date": "2025-10-01",
    "timestamp": "2025-10-01T10:52:09.643849",
    "timeframes": [
      "1D",
      "1W",
      "1M"
    ],
    "total_symbols": 304,
    "successful_fetches": 297,
    "failed_fetches": 7,
    "success_rate": 97.69736842105263,
    "timeframe_stats": {
      "1D": {
        "successful": 297,
        "total": 297,
        "success_rate": 100.0
      },
      "1W": {
        "successful": 297,
        "total": 297,
        "success_rate": 100.0
      },
      "1M": {
        "successful": 293,
        "total": 297,
        "success_rate": 98.65319865319864
      }
    },
    "scraper_config": {
      "max_workers": 1,
      "batch_size": 50,
      "rate_limit_delay": 2.0,
      "retry_count": 3
    },
    "version": "2.0"
  },
  "data": {
    "CSELK-ABAN.N0000": {
      "rsi_data": {
        "1D": 74.65,
        "1W": 85.68,
        "1M": 89.6
      },
      "status": "success",
      "successful_timeframes": 3,
      "timestamp": "2025-10-01T09:15:16.886189",
      "attempts": 1
    },
    "CSELK-AFSL.N0000": {
      "rsi_data": {
        "1D": 47.4,
        "1W": 62.3,
        "1M": 78.2
      },
      "status": "success",
      "successful_timeframes": 3,
      "timestamp": "2025-10-01T09:15:32.804617",
      "attempts": 1
    },
    "CSELK-AEL.N0000": {
      "rsi_data": {
        "1D": 65.3,
        "1W": 71.8,
        "1M": 85.9
      },
      "status": "success",
      "successful_timeframes": 3,
      "timestamp": "2025-10-01T09:15:48.589412",
      "attempts": 1
    },
    "CSELK-ACL.N0000": {
      "rsi_data": {
        "1D": 76.67,
        "1W": 79.84,
        "1M": 81.41
      },
      "status": "success",
      "successful_timeframes": 3,
      "timestamp": "2025-10-01T09:16:04.543512",
      "attempts": 1
    },
    "CSELK-APLA.N0000": {
      "rsi_data": {
        "1D": 80.17,
        "1W": 94.11,
        "1M": 88.15
      },
      "status": "success",
      "successful_timeframes": 3,
      "timestamp": "2025-10-01T09:16:20.392586",
      "attempts": 1
    },
    "CSELK-ACME.N0000": {
      "rsi_data": {
        "1D": 58.8,
        "1W": 68.9,
        "1M": 61.3
      },
      "status": "success",
      "successful_timeframes": 3,
      "timestamp": "2025-10-01T09:16:36.604101",
      "attempts": 1
    },
    "CSELK-AGAL.N0000": {
      "rsi_data": {
        "1D": 69.7,
        "1W": 75.1,
        "1M": 69.9
      },
      "status": "success",
      "successful_timeframes": 3,
      "timestamp": "2025-10-01T09:16:52.570528",
      "attempts": 1
    },
    "CSELK-AGST.N0000": {
      "rsi_data": {
        "1D": 55.9,
        "1W": 64.8,
        "1M": 54.1
      },
      "status": "success",
      "successful_timeframes": 3,
      "timestamp": "2025-10-01T09:17:08.364919",
      "attempts": 1
    },
    "CSELK-AGST.X0000": {
      "rsi_data": {
        "1D": 76.6,
        "1W": 85.2,
        "1M": 98.9
      },
      "status": "success",
      "successful_timeframes": 3,
      "timestamp": "2025-10-01T09:17:24.804415",
      "attempts": 1
    },
    "CSELK-AHUN.N0000": {
      "rsi_data": {
        "1D": 78.44,
        "1W": 82.1,
        "1M": 79.11
      },
      "status": "success",
      "successful_timeframes": 3,
      "timestamp": "2025-10-01T09:17:40.998248",
      "attempts": 1
    },
    "CSELK-ASPM.N0000": {
      "rsi_data": null,
      "status": "failed",
      "error": "Page did not load properly (attempt 3)",
      "timestamp": "2025-10-01T09:19:57.415944",
      "attempts": 3
    },
    "CSELK-SPEN.N0000": {
      "rsi_data": {
        "1D": 59.71,
        "1W": 63.79,
        "1M": 64.02
      },
      "status": "success",
      "successful_timeframes": 3,
      "timestamp": "2025-10-01T09:20:13.709534",
      "attempts": 1
    },
    "CSELK-ALLI.N0000": {
      "rsi_data": {
        "1D": 60.59,
        "1W": 66.64,
        "1M": 86.97
      },
      "status": "success",
      "successful_timeframes": 3,
      "timestamp": "2025-10-01T09:20:29.492345",
      "attempts": 1
    },
    "CSELK-AFS.N0000": {
      "rsi_data": {
        "1D": 53.3,
        "1W": 72.8,
        "1M": 86.3
      },
      "status": "success",
      "successful_timeframes": 3,
      "timestamp": "2025-10-01T09:20:45.342065",
      "attempts": 1
    },
    "CSELK-ALUM.N0000": {
      "rsi_data": {
        "1D": 74.0,
        "1W": 72.6,
        "1M": 78.4
      },
      "status": "success",
      "successful_timeframes": 3,
      "timestamp": "2025-10-01T09:21:01.060890",
      "attempts": 1
    },
    "CSELK-ABL.N0000": {
      "rsi_data": {
        "1D": 56.8,
        "1W": 64.4,
        "1M": 59.7
      },
      "status": "success",
      "successful_timeframes": 3,
      "timestamp": "2025-10-01T09:21:16.912978",
      "attempts": 1
    },
    "CSELK-ATL.N0000": {
      "rsi_data": {
        "1D": 60.0,
        "1W": 76.1,
        "1M": 78.2
      },
      "status": "success",
      "successful_timeframes": 3,
      "timestamp": "2025-10-01T09:21:32.226262",
      "attempts": 1
    },
    "CSELK-ATLL.N0000": {
      "rsi_data": {
        "1D": 49.6,
        "1W": 60.6,
        "1M": 65.7
      },
      "status": "success",
      "successful_timeframes": 3,
      "timestamp": "2025-10-01T09:21:47.558351",
      "attempts": 1
    },
    "CSELK-GREG.N0000": {
      "rsi_data": {
        "1D": 64.49,
        "1W": 70.42,
        "1M": 75.37
      },
      "status": "success",
      "successful_timeframes": 3,
      "timestamp": "2025-10-01T09:22:03.354041",
      "attempts": 1
    },
    "CSELK-AMCL.N0000": {
      "rsi_data": null,
      "status": "failed",
      "error": "Page did not load properly (attempt 3)",
      "timestamp": "2025-10-01T09:24:20.699294",
      "attempts": 3
    },
    "CSELK-ALHP.N0000": {
      "rsi_data": {
        "1D": 39.6,
        "1W": 38.5,
        "1M": 43.4
      },
      "status": "success",
      "successful_timeframes": 3,
      "timestamp": "2025-10-01T09:24:36.597964",
      "attempts": 1
    },
    "CSELK-AINS.N0000": {
      "rsi_data": {
        "1D": 47.6,
        "1W": 59.5,
        "1M": 67.0
      },
      "status": "success",
      "successful_timeframes": 3,
      "timestamp": "2025-10-01T09:24:52.382585",
      "attempts": 1
    },
    "CSELK-AAF.N0000": {
      "rsi_data": {
        "1D": 77.2,
        "1W": 85.8,
        "1M": 87.3
      },
      "status": "success",
      "successful_timeframes": 3,
      "timestamp": "2025-10-01T09:25:08.098486",
      "attempts": 1
    },
    "CSELK-AAF.P0000": {
      "rsi_data": {
        "1D": 70.6,
        "1W": 74.6,
        "1M": 83.6
      },
      "status": "success",
      "successful_timeframes": 3,
      "timestamp": "2025-10-01T09:25:24.014065",
      "attempts": 1
    },
    "CSELK-ACAP.N0000": {
      "rsi_data": {
        "1D": 54.6,
        "1W": 59.6,
        "1M": 61.6
      },
      "status": "success",
      "successful_timeframes": 3,
      "timestamp": "2025-10-01T09:25:40.012965",
      "attempts": 1
    },
    "CSELK-ASIY.N0000": {
      "rsi_data": {
        "1D": 55.4,
        "1W": 67.4,
        "1M": 77.2
      },
      "status": "success",
      "successful_timeframes": 3,
      "timestamp": "2025-10-01T09:25:55.883764",
      "attempts": 1
    },
    "CSELK-AHPL.N0000": {
      "rsi_data": {
        "1D": 47.1,
        "1W": 60.8,
        "1M": 61.9
      },
      "status": "success",
      "successful_timeframes": 3,
      "timestamp": "2025-10-01T09:26:11.377664",
      "attempts": 1
    },
    "CSELK-AMSL.N0000": {
      "rsi_data": {
        "1D": 43.4,
        "1W": 56.0,
        "1M": 57.0
      },
      "status": "success",
      "successful_timeframes": 3,
      "timestamp": "2025-10-01T09:26:27.093753",
      "attempts": 1
    },
    "CSELK-ASIR.N0000": {
      "rsi_data": {
        "1D": 52.3,
        "1W": 66.4,
        "1M": 72.4
      },
      "status": "success",
      "successful_timeframes": 3,
      "timestamp": "2025-10-01T09:26:43.025552",
      "attempts": 1
    },
    "CSELK-AMF.N0000": {
      "rsi_data": {
        "1D": 26.0,
        "1W": 53.7,
        "1M": 67.9
      },
      "status": "success",
      "successful_timeframes": 3,
      "timestamp": "2025-10-01T09:26:59.747868",
      "attempts": 1
    },
    "CSELK-AGPL.N0000": {
      "rsi_data": {
        "1D": 61.2,
        "1W": 67.4,
        "1M": 81.3
      },
      "status": "success",
      "successful_timeframes": 3,
      "timestamp": "2025-10-01T09:27:15.610329",
      "attempts": 1
    },
    "CSELK-BPPL.N0000": {
      "rsi_data": {
        "1D": 56.7,
        "1W": 57.4,
        "1M": 53.7
      },
      "status": "success",
      "successful_timeframes": 3,
      "timestamp": "2025-10-01T09:27:30.917967",
      "attempts": 1
    },
    "CSELK-BFL.N0000": {
      "rsi_data": {
        "1D": 92.31,
        "1W": 85.46,
        "1M": 80.81
      },
      "status": "success",
      "successful_timeframes": 3,
      "timestamp": "2025-10-01T09:27:46.982838",
      "attempts": 1
    },
    "CSELK-BALA.N0000": {
      "rsi_data": {
        "1D": 72.1,
        "1W": 73.78,
        "1M": 70.16
      },
      "status": "success",
      "successful_timeframes": 3,
      "timestamp": "2025-10-01T09:28:03.224489",
      "attempts": 1
    },
    "CSELK-BRR.N0000": {
      "rsi_data": {
        "1D": 54.6,
        "1W": 62.8,
        "1M": 74.3
      },
      "status": "success",
      "successful_timeframes": 3,
      "timestamp": "2025-10-01T09:28:19.434463",
      "attempts": 1
    },
    "CSELK-BERU.N0000": {
      "rsi_data": {
        "1D": 55.6,
        "1W": 56.2,
        "1M": 67.6
      },
      "status": "success",
      "successful_timeframes": 3,
      "timestamp": "2025-10-01T09:28:34.612001",
      "attempts": 1
    },
    "CSELK-BLI.N0000": {
      "rsi_data": {
        "1D": 48.4,
        "1W": 48.3,
        "1M": 36.9
      },
      "status": "success",
      "successful_timeframes": 3,
      "timestamp": "2025-10-01T09:28:50.965402",
      "attempts": 1
    },
    "CSELK-BLUE.X0000": {
      "rsi_data": {
        "1D": 47.0,
        "1W": 44.1,
        "1M": 45.3
      },
      "status": "success",
      "successful_timeframes": 3,
      "timestamp": "2025-10-01T09:29:06.946447",
      "attempts": 1
    },
    "CSELK-BLUE.N0000": {
      "rsi_data": {
        "1D": 43.0,
        "1W": 28.1,
        "1M": 41.1
      },
      "status": "success",
      "successful_timeframes": 3,
      "timestamp": "2025-10-01T09:29:25.838875",
      "attempts": 1
    },
    "CSELK-BOGA.N0000": {
      "rsi_data": {
        "1D": 63.0,
        "1W": 64.3,
        "1M": 71.1
      },
      "status": "success",
      "successful_timeframes": 3,
      "timestamp": "2025-10-01T09:29:42.117002",
      "attempts": 1
    },
    "CSELK-BOPL.N0000": {
      "rsi_data": {
        "1D": 65.9,
        "1W": 76.4,
        "1M": 75.2
      },
      "status": "success",
      "successful_timeframes": 3,
      "timestamp": "2025-10-01T09:29:57.703461",
      "attempts": 1
    },
    "CSELK-BRWN.N0000": {
      "rsi_data": {
        "1D": 48.18,
        "1W": 53.15,
        "1M": 59.53
      },
      "status": "success",
      "successful_timeframes": 3,
      "timestamp": "2025-10-01T09:30:13.319437",
      "attempts": 1
    },
    "CSELK-BBH.N0000": {
      "rsi_data": {
        "1D": 58.2,
        "1W": 66.7,
        "1M": 74.2
      },
      "status": "success",
      "successful_timeframes": 3,
      "timestamp": "2025-10-01T09:30:29.249755",
      "attempts": 1
    },
    "CSELK-BIL.N0000": {
      "rsi_data": {
        "1D": 50.0,
        "1W": 51.5,
        "1M": 54.3
      },
      "status": "success",
      "successful_timeframes": 3,
      "timestamp": "2025-10-01T09:30:45.189785",
      "attempts": 1
    },
    "CSELK-BUKI.N0000": {
      "rsi_data": {
        "1D": 57.21,
        "1W": 79.54,
        "1M": 79.56
      },
      "status": "success",
      "successful_timeframes": 3,
      "timestamp": "2025-10-01T09:31:01.116626",
      "attempts": 1
    },
    "CSELK-COLO.N0000": {
      "rsi_data": {
        "1D": 76.77,
        "1W": 80.91,
        "1M": 92.78
      },
      "status": "success",
      "successful_timeframes": 3,
      "timestamp": "2025-10-01T09:31:16.937526",
      "attempts": 1
    },
    "CSELK-CTHR.N0000": {
      "rsi_data": {
        "1D": 51.3,
        "1W": 79.25,
        "1M": 87.94
      },
      "status": "success",
      "successful_timeframes": 3,
      "timestamp": "2025-10-01T09:31:32.724547",
      "attempts": 1
    },
    "CSELK-CTLD.N0000": {
      "rsi_data": {
        "1D": 44.8,
        "1W": 56.7,
        "1M": 62.6
      },
      "status": "success",
      "successful_timeframes": 3,
      "timestamp": "2025-10-01T09:31:48.748994",
      "attempts": 1
    },
    "CSELK-CWM.N0000": {
      "rsi_data": {
        "1D": 50.11,
        "1W": 55.84,
        "1M": 67.58
      },
      "status": "success",
      "successful_timeframes": 3,
      "timestamp": "2025-10-01T09:32:05.001295",
      "attempts": 1
    },
    "CSELK-CSLK.N0000": {
      "rsi_data": {
        "1D": 51.3,
        "1W": 62.7,
        "1M": 79.0
      },
      "status": "success",
      "successful_timeframes": 3,
      "timestamp": "2025-10-01T09:32:20.251601",
      "attempts": 1
    },
    "CSELK-CALC.U0000": {
      "rsi_data": {
        "1D": 47.6,
        "1W": 41.3,
        "1M": null
      },
      "status": "success",
      "successful_timeframes": 2,
      "timestamp": "2025-10-01T09:33:20.813553",
      "attempts": 1
    },
    "CSELK-CALI.U0000": {
      "rsi_data": {
        "1D": 54.6,
        "1W": 55.3,
        "1M": 34.2
      },
      "status": "success",
      "successful_timeframes": 3,
      "timestamp": "2025-10-01T09:33:36.697182",
      "attempts": 1
    },
    "CSELK-CALH.N0000": {
      "rsi_data": {
        "1D": 50.5,
        "1W": 54.9,
        "1M": null
      },
      "status": "success",
      "successful_timeframes": 2,
      "timestamp": "2025-10-01T09:34:32.792886",
      "attempts": 1
    },
    "CSELK-CALT.N0000": {
      "rsi_data": {
        "1D": 39.9,
        "1W": 45.2,
        "1M": 53.8
      },
      "status": "success",
      "successful_timeframes": 3,
      "timestamp": "2025-10-01T09:34:48.674943",
      "attempts": 1
    },
    "CSELK-CARG.N0000": {
      "rsi_data": {
        "1D": 60.31,
        "1W": 80.11,
        "1M": 92.95
      },
      "status": "success",
      "successful_timeframes": 3,
      "timestamp": "2025-10-01T09:35:04.562448",
      "attempts": 1
    },
    "CSELK-CBNK.N0000": {
      "rsi_data": {
        "1D": 49.7,
        "1W": 56.5,
        "1M": 61.2
      },
      "status": "success",
      "successful_timeframes": 3,
      "timestamp": "2025-10-01T09:35:20.228795",
      "attempts": 1
    },
    "CSELK-CABO.N0000": {
      "rsi_data": {
        "1D": 47.81,
        "1W": 67.06,
        "1M": 75.97
      },
      "status": "success",
      "successful_timeframes": 3,
      "timestamp": "2025-10-01T09:35:35.973742",
      "attempts": 1
    },
    "CSELK-CARS.N0000": {
      "rsi_data": {
        "1D": 66.37,
        "1W": 84.88,
        "1M": 86.44
      },
      "status": "success",
      "successful_timeframes": 3,
      "timestamp": "2025-10-01T09:35:51.086726",
      "attempts": 1
    },
    "CSELK-CFIN.N0000": {
      "rsi_data": {
        "1D": 68.64,
        "1W": 74.39,
        "1M": 78.35
      },
      "status": "success",
      "successful_timeframes": 3,
      "timestamp": "2025-10-01T09:36:07.839498",
      "attempts": 1
    },
    "CSELK-CIND.N0000": {
      "rsi_data": {
        "1D": 71.89,
        "1W": 83.22,
        "1M": 74.68
      },
      "status": "success",
      "successful_timeframes": 3,
      "timestamp": "2025-10-01T09:36:23.719007",
      "attempts": 1
    },
    "CSELK-CINS.X0000": {
      "rsi_data": {
        "1D": 60.37,
        "1W": 75.58,
        "1M": 81.52
      },
      "status": "success",
      "successful_timeframes": 3,
      "timestamp": "2025-10-01T09:36:39.607326",
      "attempts": 1
    },
    "CSELK-CINS.N0000": {
      "rsi_data": {
        "1D": 57.3,
        "1W": 57.58,
        "1M": 61.04
      },
      "status": "success",
      "successful_timeframes": 3,
      "timestamp": "2025-10-01T09:36:55.341490",
      "attempts": 1
    },
    "CSELK-BREW.N0000": {
      "rsi_data": {
        "1D": 54.47,
        "1W": 53.94,
        "1M": 70.38
      },
      "status": "success",
      "successful_timeframes": 3,
      "timestamp": "2025-10-01T09:37:11.373787",
      "attempts": 1
    },
    "CSELK-CCS.N0000": {
      "rsi_data": {
        "1D": 76.54,
        "1W": 74.35,
        "1M": 79.17
      },
      "status": "success",
      "successful_timeframes": 3,
      "timestamp": "2025-10-01T09:37:27.796865",
      "attempts": 1
    },
    "CSELK-GRAN.N0000": {
      "rsi_data": {
        "1D": 73.56,
        "1W": 76.16,
        "1M": 85.83
      },
      "status": "success",
      "successful_timeframes": 3,
      "timestamp": "2025-10-01T09:37:43.904997",
      "attempts": 1
    },
    "CSELK-GUAR.N0000": {
      "rsi_data": {
        "1D": 66.16,
        "1W": 79.1,
        "1M": 83.02
      },
      "status": "success",
      "successful_timeframes": 3,
      "timestamp": "2025-10-01T09:38:00.025849",
      "attempts": 1
    },
    "CSELK-CHL.X0000": {
      "rsi_data": {
        "1D": 49.33,
        "1W": 75.62,
        "1M": 70.18
      },
      "status": "success",
      "successful_timeframes": 3,
      "timestamp": "2025-10-01T09:38:15.424999",
      "attempts": 1
    },
    "CSELK-CHL.N0000": {
      "rsi_data": {
        "1D": 56.6,
        "1W": 69.44,
        "1M": 76.65
      },
      "status": "success",
      "successful_timeframes": 3,
      "timestamp": "2025-10-01T09:38:31.257436",
      "attempts": 1
    },
    "CSELK-CHOT.N0000": {
      "rsi_data": {
        "1D": 79.9,
        "1W": 85.9,
        "1M": 82.2
      },
      "status": "success",
      "successful_timeframes": 3,
      "timestamp": "2025-10-01T09:38:46.723407",
      "attempts": 1
    },
    "CSELK-CINV.N0000": {
      "rsi_data": {
        "1D": 62.76,
        "1W": 71.1,
        "1M": 76.44
      },
      "status": "success",
      "successful_timeframes": 3,
      "timestamp": "2025-10-01T09:39:02.972339",
      "attempts": 1
    },
    "CSELK-KZOO.N0000": {
      "rsi_data": {
        "1D": 59.5,
        "1W": 60.4,
        "1M": 61.1
      },
      "status": "success",
      "successful_timeframes": 3,
      "timestamp": "2025-10-01T09:39:18.965202",
      "attempts": 1
    },
    "CSELK-CPRT.N0000": {
      "rsi_data": {
        "1D": 61.36,
        "1W": 66.36,
        "1M": 65.0
      },
      "status": "success",
      "successful_timeframes": 3,
      "timestamp": "2025-10-01T09:39:34.628025",
      "attempts": 1
    },
    "CSELK-CTBL.N0000": {
      "rsi_data": {
        "1D": 54.7,
        "1W": 63.0,
        "1M": 67.4
      },
      "status": "success",
      "successful_timeframes": 3,
      "timestamp": "2025-10-01T09:39:50.692872",
      "attempts": 1
    },
    "CSELK-CTC.N0000": {
      "rsi_data": {
        "1D": 73.45,
        "1W": 69.1,
        "1M": 78.41
      },
      "status": "success",
      "successful_timeframes": 3,
      "timestamp": "2025-10-01T09:40:06.515713",
      "attempts": 1
    },
    "CSELK-CHMX.N0000": {
      "rsi_data": {
        "1D": 53.61,
        "1W": 63.02,
        "1M": 69.71
      },
      "status": "success",
      "successful_timeframes": 3,
      "timestamp": "2025-10-01T09:40:22.057020",
      "attempts": 1
    },
    "CSELK-LLUB.N0000": {
      "rsi_data": {
        "1D": 57.4,
        "1W": 65.86,
        "1M": 70.34
      },
      "status": "success",
      "successful_timeframes": 3,
      "timestamp": "2025-10-01T09:40:37.525457",
      "attempts": 1
    },
    "CSELK-CWL.N0000": {
      "rsi_data": {
        "1D": 63.7,
        "1W": 69.4,
        "1M": 61.2
      },
      "status": "success",
      "successful_timeframes": 3,
      "timestamp": "2025-10-01T09:40:53.477520",
      "attempts": 1
    },
    "CSELK-CIC.X0000": {
      "rsi_data": {
        "1D": 77.23,
        "1W": 79.79,
        "1M": 81.92
      },
      "status": "success",
      "successful_timeframes": 3,
      "timestamp": "2025-10-01T09:41:09.908998",
      "attempts": 1
    },
    "CSELK-CIC.N0000": {
      "rsi_data": {
        "1D": 84.0,
        "1W": 76.87,
        "1M": 83.34
      },
      "status": "success",
      "successful_timeframes": 3,
      "timestamp": "2025-10-01T09:41:26.872984",
      "attempts": 1
    },
    "CSELK-CDB.N0000": {
      "rsi_data": {
        "1D": 57.82,
        "1W": 66.56,
        "1M": 75.16
      },
      "status": "success",
      "successful_timeframes": 3,
      "timestamp": "2025-10-01T09:41:41.884818",
      "attempts": 1
    },
    "CSELK-CDB.X0000": {
      "rsi_data": {
        "1D": 65.26,
        "1W": 68.01,
        "1M": 82.49
      },
      "status": "success",
      "successful_timeframes": 3,
      "timestamp": "2025-10-01T09:41:58.110092",
      "attempts": 1
    },
    "CSELK-REEF.N0000": {
      "rsi_data": {
        "1D": 51.2,
        "1W": 56.0,
        "1M": 45.3
      },
      "status": "success",
      "successful_timeframes": 3,
      "timestamp": "2025-10-01T09:42:14.130104",
      "attempts": 1
    },
    "CSELK-CHOU.N0000": {
      "rsi_data": {
        "1D": 32.1,
        "1W": 31.8,
        "1M": 33.0
      },
      "status": "success",
      "successful_timeframes": 3,
      "timestamp": "2025-10-01T09:42:30.353857",
      "attempts": 1
    },
    "CSELK-COOP.N0000": {
      "rsi_data": {
        "1D": 40.5,
        "1W": 58.7,
        "1M": 59.0
      },
      "status": "success",
      "successful_timeframes": 3,
      "timestamp": "2025-10-01T09:42:46.322099",
      "attempts": 1
    },
    "CSELK-PHAR.N0000": {
      "rsi_data": {
        "1D": 55.68,
        "1W": 73.46,
        "1M": 79.84
      },
      "status": "success",
      "successful_timeframes": 3,
      "timestamp": "2025-10-01T09:43:01.908677",
      "attempts": 1
    },
    "CSELK-DOCK.N0000": {
      "rsi_data": {
        "1D": 66.01,
        "1W": 70.94,
        "1M": 77.94
      },
      "status": "success",
      "successful_timeframes": 3,
      "timestamp": "2025-10-01T09:43:18.020332",
      "attempts": 1
    },
    "CSELK-CFI.N0000": {
      "rsi_data": {
        "1D": 48.65,
        "1W": 75.87,
        "1M": 88.64
      },
      "status": "success",
      "successful_timeframes": 3,
      "timestamp": "2025-10-01T09:43:33.303603",
      "attempts": 1
    },
    "CSELK-CIT.N0000": {
      "rsi_data": {
        "1D": 46.84,
        "1W": 69.17,
        "1M": 80.89
      },
      "status": "success",
      "successful_timeframes": 3,
      "timestamp": "2025-10-01T09:43:49.746473",
      "attempts": 1
    },
    "CSELK-CLND.N0000": {
      "rsi_data": {
        "1D": 59.6,
        "1W": 78.0,
        "1M": 76.7
      },
      "status": "success",
      "successful_timeframes": 3,
      "timestamp": "2025-10-01T09:44:05.250525",
      "attempts": 1
    },
    "CSELK-COMB.N0000": {
      "rsi_data": {
        "1D": 60.13,
        "1W": 75.81,
        "1M": 79.42
      },
      "status": "success",
      "successful_timeframes": 3,
      "timestamp": "2025-10-01T09:44:21.311892",
      "attempts": 1
    },
    "CSELK-COMB.X0000": {
      "rsi_data": {
        "1D": 72.28,
        "1W": 81.49,
        "1M": 81.17
      },
      "status": "success",
      "successful_timeframes": 3,
      "timestamp": "2025-10-01T09:44:37.220672",
      "attempts": 1
    },
    "CSELK-COCR.N0000": {
      "rsi_data": {
        "1D": 59.32,
        "1W": 79.79,
        "1M": 84.85
      },
      "status": "success",
      "successful_timeframes": 3,
      "timestamp": "2025-10-01T09:44:52.725596",
      "attempts": 1
    },
    "CSELK-COMD.N0000": {
      "rsi_data": {
        "1D": 49.97,
        "1W": 74.68,
        "1M": 77.62
      },
      "status": "success",
      "successful_timeframes": 3,
      "timestamp": "2025-10-01T09:45:08.623837",
      "attempts": 1
    },
    "CSELK-SOY.N0000": {
      "rsi_data": {
        "1D": 62.81,
        "1W": 73.28,
        "1M": 79.65
      },
      "status": "success",
      "successful_timeframes": 3,
      "timestamp": "2025-10-01T09:45:24.993981",
      "attempts": 1
    },
    "CSELK-DPL.N0000": {
      "rsi_data": {
        "1D": 32.8,
        "1W": 39.8,
        "1M": 43.9
      },
      "status": "success",
      "successful_timeframes": 3,
      "timestamp": "2025-10-01T09:45:41.322727",
      "attempts": 1
    },
    "CSELK-DFCC.N0000": {
      "rsi_data": {
        "1D": 61.72,
        "1W": 77.37,
        "1M": 77.9
      },
      "status": "success",
      "successful_timeframes": 3,
      "timestamp": "2025-10-01T09:45:57.612360",
      "attempts": 1
    },
    "CSELK-DIAL.N0000": {
      "rsi_data": {
        "1D": 77.0,
        "1W": 87.2,
        "1M": 86.4
      },
      "status": "success",
      "successful_timeframes": 3,
      "timestamp": "2025-10-01T09:46:13.050455",
      "attempts": 1
    },
    "CSELK-CALF.N0000": {
      "rsi_data": {
        "1D": 63.4,
        "1W": 69.5,
        "1M": 66.9
      },
      "status": "success",
      "successful_timeframes": 3,
      "timestamp": "2025-10-01T09:46:28.438320",
      "attempts": 1
    },
    "CSELK-DIMO.N0000": {
      "rsi_data": {
        "1D": 83.01,
        "1W": 84.38,
        "1M": 83.34
      },
      "status": "success",
      "successful_timeframes": 3,
      "timestamp": "2025-10-01T09:46:43.750336",
      "attempts": 1
    },
    "CSELK-PKME.N0000": {
      "rsi_data": {
        "1D": 76.32,
        "1W": 86.86,
        "1M": null
      },
      "status": "success",
      "successful_timeframes": 2,
      "timestamp": "2025-10-01T09:47:06.290293",
      "attempts": 1
    },
    "CSELK-CTEA.N0000": {
      "rsi_data": {
        "1D": 51.85,
        "1W": 57.07,
        "1M": 59.46
      },
      "status": "success",
      "successful_timeframes": 3,
      "timestamp": "2025-10-01T09:47:26.021545",
      "attempts": 1
    },
    "CSELK-DIPD.N0000": {
      "rsi_data": {
        "1D": 72.9,
        "1W": 65.2,
        "1M": 72.7
      },
      "status": "success",
      "successful_timeframes": 3,
      "timestamp": "2025-10-01T09:47:41.693031",
      "attempts": 1
    },
    "CSELK-DIST.N0000": {
      "rsi_data": {
        "1D": 83.3,
        "1W": 83.2,
        "1M": 86.3
      },
      "status": "success",
      "successful_timeframes": 3,
      "timestamp": "2025-10-01T09:47:57.808063",
      "attempts": 1
    },
    "CSELK-STAF.N0000": {
      "rsi_data": {
        "1D": 55.0,
        "1W": 66.8,
        "1M": 70.7
      },
      "status": "success",
      "successful_timeframes": 3,
      "timestamp": "2025-10-01T09:48:12.911313",
      "attempts": 1
    },
    "CSELK-ASCO.N0000": {
      "rsi_data": {
        "1D": 54.9,
        "1W": 69.8,
        "1M": 75.5
      },
      "status": "success",
      "successful_timeframes": 3,
      "timestamp": "2025-10-01T09:48:28.149788",
      "attempts": 1
    },
    "CSELK-ASHO.N0000": {
      "rsi_data": {
        "1D": 81.27,
        "1W": 86.66,
        "1M": 90.27
      },
      "status": "success",
      "successful_timeframes": 3,
      "timestamp": "2025-10-01T09:48:43.756621",
      "attempts": 1
    },
    "CSELK-ASPH.N0000": {
      "rsi_data": {
        "1D": 53.2,
        "1W": 55.3,
        "1M": 60.1
      },
      "status": "success",
      "successful_timeframes": 3,
      "timestamp": "2025-10-01T09:48:59.697562",
      "attempts": 1
    },
    "CSELK-BFN.N0000": {
      "rsi_data": {
        "1D": 41.0,
        "1W": 61.7,
        "1M": 71.5
      },
      "status": "success",
      "successful_timeframes": 3,
      "timestamp": "2025-10-01T09:49:15.977976",
      "attempts": 1
    },
    "CSELK-CERA.N0000": {
      "rsi_data": {
        "1D": 51.37,
        "1W": 59.34,
        "1M": 71.52
      },
      "status": "success",
      "successful_timeframes": 3,
      "timestamp": "2025-10-01T09:49:32.187102",
      "attempts": 1
    },
    "CSELK-CFVF.N0000": {
      "rsi_data": {
        "1D": 77.8,
        "1W": 84.4,
        "1M": 75.1
      },
      "status": "success",
      "successful_timeframes": 3,
      "timestamp": "2025-10-01T09:49:47.968706",
      "attempts": 1
    },
    "CSELK-CITH.N0000": {
      "rsi_data": {
        "1D": 47.2,
        "1W": 52.3,
        "1M": 44.3
      },
      "status": "success",
      "successful_timeframes": 3,
      "timestamp": "2025-10-01T09:50:03.315090",
      "attempts": 1
    },
    "CSELK-CONN.N0000": {
      "rsi_data": {
        "1D": 65.1,
        "1W": 71.6,
        "1M": 74.6
      },
      "status": "success",
      "successful_timeframes": 3,
      "timestamp": "2025-10-01T09:50:19.672085",
      "attempts": 1
    },
    "CSELK-CSF.N0000": {
      "rsi_data": {
        "1D": 46.4,
        "1W": 37.1,
        "1M": 34.5
      },
      "status": "success",
      "successful_timeframes": 3,
      "timestamp": "2025-10-01T09:50:35.245363",
      "attempts": 1
    },
    "CSELK-EAST.N0000": {
      "rsi_data": {
        "1D": 56.1,
        "1W": 74.4,
        "1M": 93.2
      },
      "status": "success",
      "successful_timeframes": 3,
      "timestamp": "2025-10-01T09:50:51.138522",
      "attempts": 1
    },
    "CSELK-EBCR.N0000": {
      "rsi_data": {
        "1D": 50.5,
        "1W": 69.7,
        "1M": 80.4
      },
      "status": "success",
      "successful_timeframes": 3,
      "timestamp": "2025-10-01T09:51:06.993408",
      "attempts": 1
    },
    "CSELK-ECL.N0000": {
      "rsi_data": {
        "1D": 53.4,
        "1W": 59.6,
        "1M": 57.5
      },
      "status": "success",
      "successful_timeframes": 3,
      "timestamp": "2025-10-01T09:51:22.601306",
      "attempts": 1
    },
    "CSELK-EDEN.N0000": {
      "rsi_data": {
        "1D": 54.1,
        "1W": 55.0,
        "1M": 54.9
      },
      "status": "success",
      "successful_timeframes": 3,
      "timestamp": "2025-10-01T09:51:38.433099",
      "attempts": 1
    },
    "CSELK-ELPL.N0000": {
      "rsi_data": {
        "1D": 75.11,
        "1W": 81.06,
        "1M": 80.0
      },
      "status": "success",
      "successful_timeframes": 3,
      "timestamp": "2025-10-01T09:51:53.785385",
      "attempts": 1
    },
    "CSELK-EMER.N0000": {
      "rsi_data": {
        "1D": 52.9,
        "1W": 60.9,
        "1M": 63.0
      },
      "status": "success",
      "successful_timeframes": 3,
      "timestamp": "2025-10-01T09:52:10.568884",
      "attempts": 1
    },
    "CSELK-EML.N0000": {
      "rsi_data": {
        "1D": 51.6,
        "1W": 60.3,
        "1M": 47.5
      },
      "status": "success",
      "successful_timeframes": 3,
      "timestamp": "2025-10-01T09:52:26.089236",
      "attempts": 1
    },
    "CSELK-ETWO.N0000": {
      "rsi_data": {
        "1D": 59.2,
        "1W": 72.5,
        "1M": 80.3
      },
      "status": "success",
      "successful_timeframes": 3,
      "timestamp": "2025-10-01T09:52:41.855467",
      "attempts": 1
    },
    "CSELK-EXT.N0000": {
      "rsi_data": {
        "1D": 68.3,
        "1W": 74.6,
        "1M": 62.6
      },
      "status": "success",
      "successful_timeframes": 3,
      "timestamp": "2025-10-01T09:52:57.612312",
      "attempts": 1
    },
    "CSELK-FCT.N0000": {
      "rsi_data": {
        "1D": 76.6,
        "1W": 85.6,
        "1M": 72.1
      },
      "status": "success",
      "successful_timeframes": 3,
      "timestamp": "2025-10-01T09:53:13.091214",
      "attempts": 1
    },
    "CSELK-GEST.N0000": {
      "rsi_data": {
        "1D": 51.53,
        "1W": 63.99,
        "1M": 67.54
      },
      "status": "success",
      "successful_timeframes": 3,
      "timestamp": "2025-10-01T09:53:29.363954",
      "attempts": 1
    },
    "CSELK-GHLL.N0000": {
      "rsi_data": {
        "1D": 68.7,
        "1W": 70.7,
        "1M": 66.1
      },
      "status": "success",
      "successful_timeframes": 3,
      "timestamp": "2025-10-01T09:53:45.360100",
      "attempts": 1
    },
    "CSELK-HAPU.N0000": {
      "rsi_data": {
        "1D": 79.3,
        "1W": 85.1,
        "1M": 76.5
      },
      "status": "success",
      "successful_timeframes": 3,
      "timestamp": "2025-10-01T09:54:01.047943",
      "attempts": 1
    },
    "CSELK-HARI.N0000": {
      "rsi_data": {
        "1D": 55.48,
        "1W": 60.98,
        "1M": 55.67
      },
      "status": "success",
      "successful_timeframes": 3,
      "timestamp": "2025-10-01T09:54:16.202462",
      "attempts": 1
    },
    "CSELK-HASU.N0000": {
      "rsi_data": {
        "1D": 50.6,
        "1W": 66.65,
        "1M": 74.59
      },
      "status": "success",
      "successful_timeframes": 3,
      "timestamp": "2025-10-01T09:54:32.057763",
      "attempts": 1
    },
    "CSELK-HAYC.N0000": {
      "rsi_data": {
        "1D": 74.4,
        "1W": 69.5,
        "1M": 72.1
      },
      "status": "success",
      "successful_timeframes": 3,
      "timestamp": "2025-10-01T09:54:47.929443",
      "attempts": 1
    },
    "CSELK-HAYL.N0000": {
      "rsi_data": {
        "1D": 62.5,
        "1W": 67.47,
        "1M": 74.14
      },
      "status": "success",
      "successful_timeframes": 3,
      "timestamp": "2025-10-01T09:55:03.841500",
      "attempts": 1
    },
    "CSELK-HBS.N0000": {
      "rsi_data": {
        "1D": 44.7,
        "1W": 51.2,
        "1M": 38.1
      },
      "status": "success",
      "successful_timeframes": 3,
      "timestamp": "2025-10-01T09:55:19.397964",
      "attempts": 1
    },
    "CSELK-HDFC.N0000": {
      "rsi_data": {
        "1D": 40.7,
        "1W": 46.5,
        "1M": 55.3
      },
      "status": "success",
      "successful_timeframes": 3,
      "timestamp": "2025-10-01T09:55:34.893891",
      "attempts": 1
    },
    "CSELK-HELA.N0000": {
      "rsi_data": {
        "1D": 46.5,
        "1W": 40.3,
        "1M": 32.6
      },
      "status": "success",
      "successful_timeframes": 3,
      "timestamp": "2025-10-01T09:55:51.240564",
      "attempts": 1
    },
    "CSELK-HEXP.N0000": {
      "rsi_data": {
        "1D": 54.6,
        "1W": 70.9,
        "1M": 69.1
      },
      "status": "success",
      "successful_timeframes": 3,
      "timestamp": "2025-10-01T09:56:06.702257",
      "attempts": 1
    },
    "CSELK-HHL.N0000": {
      "rsi_data": {
        "1D": 75.8,
        "1W": 73.9,
        "1M": 86.0
      },
      "status": "success",
      "successful_timeframes": 3,
      "timestamp": "2025-10-01T09:56:22.877393",
      "attempts": 1
    },
    "CSELK-HNB.N0000": {
      "rsi_data": {
        "1D": 51.8,
        "1W": 69.59,
        "1M": 73.79
      },
      "status": "success",
      "successful_timeframes": 3,
      "timestamp": "2025-10-01T09:56:38.323106",
      "attempts": 1
    },
    "CSELK-HNB.X0000": {
      "rsi_data": {
        "1D": 44.24,
        "1W": 59.35,
        "1M": 70.59
      },
      "status": "success",
      "successful_timeframes": 3,
      "timestamp": "2025-10-01T09:56:53.761310",
      "attempts": 1
    },
    "CSELK-HNBF.N0000": {
      "rsi_data": {
        "1D": 52.2,
        "1W": 72.6,
        "1M": 69.3
      },
      "status": "success",
      "successful_timeframes": 3,
      "timestamp": "2025-10-01T09:57:10.371278",
      "attempts": 1
    },
    "CSELK-HNBF.R0000": {
      "rsi_data": null,
      "status": "failed",
      "error": "Page did not load properly (attempt 3)",
      "timestamp": "2025-10-01T09:59:29.284339",
      "attempts": 3
    },
    "CSELK-HNBF.R0001": {
      "rsi_data": null,
      "status": "failed",
      "error": "Page did not load properly (attempt 3)",
      "timestamp": "2025-10-01T10:01:46.311754",
      "attempts": 3
    },
    "CSELK-HNBF.X0000": {
      "rsi_data": {
        "1D": 42.2,
        "1W": 54.0,
        "1M": 57.6
      },
      "status": "success",
      "successful_timeframes": 3,
      "timestamp": "2025-10-01T10:02:01.746913",
      "attempts": 1
    },
    "CSELK-HOPL.N0000": {
      "rsi_data": {
        "1D": 59.0,
        "1W": 67.2,
        "1M": 63.6
      },
      "status": "success",
      "successful_timeframes": 3,
      "timestamp": "2025-10-01T10:02:17.671927",
      "attempts": 1
    },
    "CSELK-HPFL.N0000": {
      "rsi_data": {
        "1D": 49.7,
        "1W": 59.0,
        "1M": 67.2
      },
      "status": "success",
      "successful_timeframes": 3,
      "timestamp": "2025-10-01T10:02:33.740652",
      "attempts": 1
    },
    "CSELK-HPL.N0000": {
      "rsi_data": {
        "1D": 53.2,
        "1W": 58.9,
        "1M": 61.4
      },
      "status": "success",
      "successful_timeframes": 3,
      "timestamp": "2025-10-01T10:02:49.873335",
      "attempts": 1
    },
    "CSELK-HSIG.N0000": {
      "rsi_data": {
        "1D": 65.36,
        "1W": 74.87,
        "1M": 77.62
      },
      "status": "success",
      "successful_timeframes": 3,
      "timestamp": "2025-10-01T10:03:05.172104",
      "attempts": 1
    },
    "CSELK-HUNA.N0000": {
      "rsi_data": {
        "1D": 54.8,
        "1W": 45.0,
        "1M": 42.6
      },
      "status": "success",
      "successful_timeframes": 3,
      "timestamp": "2025-10-01T10:03:21.298960",
      "attempts": 1
    },
    "CSELK-HUNT.N0000": {
      "rsi_data": {
        "1D": 63.09,
        "1W": 66.44,
        "1M": 73.53
      },
      "status": "success",
      "successful_timeframes": 3,
      "timestamp": "2025-10-01T10:03:37.384229",
      "attempts": 1
    },
    "CSELK-HVA.N0000": {
      "rsi_data": {
        "1D": 55.0,
        "1W": 52.4,
        "1M": 50.9
      },
      "status": "success",
      "successful_timeframes": 3,
      "timestamp": "2025-10-01T10:03:53.506781",
      "attempts": 1
    },
    "CSELK-JAT.N0000": {
      "rsi_data": {
        "1D": 66.1,
        "1W": 77.5,
        "1M": 84.0
      },
      "status": "success",
      "successful_timeframes": 3,
      "timestamp": "2025-10-01T10:04:09.117250",
      "attempts": 1
    },
    "CSELK-JETS.N0000": {
      "rsi_data": {
        "1D": 73.0,
        "1W": 79.9,
        "1M": 77.3
      },
      "status": "success",
      "successful_timeframes": 3,
      "timestamp": "2025-10-01T10:04:26.172337",
      "attempts": 1
    },
    "CSELK-JINS.N0000": {
      "rsi_data": {
        "1D": 73.23,
        "1W": 79.92,
        "1M": 84.62
      },
      "status": "success",
      "successful_timeframes": 3,
      "timestamp": "2025-10-01T10:04:45.869236",
      "attempts": 1
    },
    "CSELK-JKH.N0000": {
      "rsi_data": {
        "1D": 44.6,
        "1W": 48.7,
        "1M": 58.3
      },
      "status": "success",
      "successful_timeframes": 3,
      "timestamp": "2025-10-01T10:05:01.073361",
      "attempts": 1
    },
    "CSELK-JKL.N0000": {
      "rsi_data": {
        "1D": 52.7,
        "1W": 57.5,
        "1M": 62.5
      },
      "status": "success",
      "successful_timeframes": 3,
      "timestamp": "2025-10-01T10:05:17.559595",
      "attempts": 1
    },
    "CSELK-KAHA.N0000": {
      "rsi_data": {
        "1D": 50.3,
        "1W": 53.8,
        "1M": 54.8
      },
      "status": "success",
      "successful_timeframes": 3,
      "timestamp": "2025-10-01T10:05:33.335791",
      "attempts": 1
    },
    "CSELK-KCAB.N0000": {
      "rsi_data": {
        "1D": 78.15,
        "1W": 90.1,
        "1M": 87.16
      },
      "status": "success",
      "successful_timeframes": 3,
      "timestamp": "2025-10-01T10:05:48.500512",
      "attempts": 1
    },
    "CSELK-KDL.N0000": {
      "rsi_data": {
        "1D": 46.2,
        "1W": 46.6,
        "1M": 45.7
      },
      "status": "success",
      "successful_timeframes": 3,
      "timestamp": "2025-10-01T10:06:04.552381",
      "attempts": 1
    },
    "CSELK-KFP.N0000": {
      "rsi_data": {
        "1D": 40.02,
        "1W": 42.23,
        "1M": 48.93
      },
      "status": "success",
      "successful_timeframes": 3,
      "timestamp": "2025-10-01T10:06:20.536243",
      "attempts": 1
    },
    "CSELK-KGAL.N0000": {
      "rsi_data": {
        "1D": 56.31,
        "1W": 60.46,
        "1M": 57.03
      },
      "status": "success",
      "successful_timeframes": 3,
      "timestamp": "2025-10-01T10:06:36.055947",
      "attempts": 1
    },
    "CSELK-KHL.N0000": {
      "rsi_data": {
        "1D": 77.3,
        "1W": 74.7,
        "1M": 69.7
      },
      "status": "success",
      "successful_timeframes": 3,
      "timestamp": "2025-10-01T10:06:51.531006",
      "attempts": 1
    },
    "CSELK-KOTA.N0000": {
      "rsi_data": {
        "1D": 68.1,
        "1W": 66.8,
        "1M": 66.6
      },
      "status": "success",
      "successful_timeframes": 3,
      "timestamp": "2025-10-01T10:07:07.486163",
      "attempts": 1
    },
    "CSELK-KPHL.N0000": {
      "rsi_data": {
        "1D": 42.1,
        "1W": 47.7,
        "1M": 42.3
      },
      "status": "success",
      "successful_timeframes": 3,
      "timestamp": "2025-10-01T10:07:23.659851",
      "attempts": 1
    },
    "CSELK-KVAL.N0000": {
      "rsi_data": {
        "1D": 57.36,
        "1W": 63.93,
        "1M": 60.85
      },
      "status": "success",
      "successful_timeframes": 3,
      "timestamp": "2025-10-01T10:07:39.211349",
      "attempts": 1
    },
    "CSELK-LALU.N0000": {
      "rsi_data": {
        "1D": 58.2,
        "1W": 69.9,
        "1M": 75.9
      },
      "status": "success",
      "successful_timeframes": 3,
      "timestamp": "2025-10-01T10:07:55.394000",
      "attempts": 1
    },
    "CSELK-LAMB.N0000": {
      "rsi_data": {
        "1D": 63.77,
        "1W": 79.5,
        "1M": 77.16
      },
      "status": "success",
      "successful_timeframes": 3,
      "timestamp": "2025-10-01T10:08:10.423764",
      "attempts": 1
    },
    "CSELK-LCBF.N0000": {
      "rsi_data": {
        "1D": 71.7,
        "1W": 81.3,
        "1M": 81.8
      },
      "status": "success",
      "successful_timeframes": 3,
      "timestamp": "2025-10-01T10:08:26.642504",
      "attempts": 1
    },
    "CSELK-LCEY.N0000": {
      "rsi_data": {
        "1D": 71.47,
        "1W": 75.65,
        "1M": 67.61
      },
      "status": "success",
      "successful_timeframes": 3,
      "timestamp": "2025-10-01T10:08:42.362171",
      "attempts": 1
    },
    "CSELK-LDEV.N0000": {
      "rsi_data": {
        "1D": 61.2,
        "1W": 70.7,
        "1M": 65.4
      },
      "status": "success",
      "successful_timeframes": 3,
      "timestamp": "2025-10-01T10:08:57.867103",
      "attempts": 1
    },
    "CSELK-LFIN.N0000": {
      "rsi_data": {
        "1D": 68.59,
        "1W": 77.09,
        "1M": 86.2
      },
      "status": "success",
      "successful_timeframes": 3,
      "timestamp": "2025-10-01T10:09:13.885547",
      "attempts": 1
    },
    "CSELK-LGIL.N0000": {
      "rsi_data": {
        "1D": 46.9,
        "1W": 53.7,
        "1M": 50.1
      },
      "status": "success",
      "successful_timeframes": 3,
      "timestamp": "2025-10-01T10:09:30.231557",
      "attempts": 1
    },
    "CSELK-LGL.N0000": {
      "rsi_data": {
        "1D": 59.9,
        "1W": 71.9,
        "1M": 73.2
      },
      "status": "success",
      "successful_timeframes": 3,
      "timestamp": "2025-10-01T10:09:45.941799",
      "attempts": 1
    },
    "CSELK-LGL.X0000": {
      "rsi_data": {
        "1D": 65.3,
        "1W": 80.2,
        "1M": 76.9
      },
      "status": "success",
      "successful_timeframes": 3,
      "timestamp": "2025-10-01T10:10:01.740508",
      "attempts": 1
    },
    "CSELK-LIOC.N0000": {
      "rsi_data": {
        "1D": 41.45,
        "1W": 48.7,
        "1M": 53.53
      },
      "status": "success",
      "successful_timeframes": 3,
      "timestamp": "2025-10-01T10:10:17.521048",
      "attempts": 1
    },
    "CSELK-LION.N0000": {
      "rsi_data": {
        "1D": 52.94,
        "1W": 59.77,
        "1M": 75.49
      },
      "status": "success",
      "successful_timeframes": 3,
      "timestamp": "2025-10-01T10:10:33.384680",
      "attempts": 1
    },
    "CSELK-LITE.N0000": {
      "rsi_data": {
        "1D": 49.5,
        "1W": 62.9,
        "1M": 85.6
      },
      "status": "success",
      "successful_timeframes": 3,
      "timestamp": "2025-10-01T10:10:49.254317",
      "attempts": 1
    },
    "CSELK-LMF.N0000": {
      "rsi_data": {
        "1D": 77.4,
        "1W": 73.7,
        "1M": 83.7
      },
      "status": "success",
      "successful_timeframes": 3,
      "timestamp": "2025-10-01T10:11:04.896018",
      "attempts": 1
    },
    "CSELK-LOFC.N0000": {
      "rsi_data": {
        "1D": 44.6,
        "1W": 39.9,
        "1M": 47.4
      },
      "status": "success",
      "successful_timeframes": 3,
      "timestamp": "2025-10-01T10:11:20.220110",
      "attempts": 1
    },
    "CSELK-LOLC.N0000": {
      "rsi_data": {
        "1D": 52.47,
        "1W": 49.23,
        "1M": 54.28
      },
      "status": "success",
      "successful_timeframes": 3,
      "timestamp": "2025-10-01T10:11:36.459225",
      "attempts": 1
    },
    "CSELK-LPL.N0000": {
      "rsi_data": {
        "1D": 55.3,
        "1W": 65.7,
        "1M": 74.2
      },
      "status": "success",
      "successful_timeframes": 3,
      "timestamp": "2025-10-01T10:11:52.689287",
      "attempts": 1
    },
    "CSELK-LPL.X0000": {
      "rsi_data": {
        "1D": 53.1,
        "1W": 63.6,
        "1M": 69.2
      },
      "status": "success",
      "successful_timeframes": 3,
      "timestamp": "2025-10-01T10:12:09.279822",
      "attempts": 1
    },
    "CSELK-LPRT.N0000": {
      "rsi_data": {
        "1D": 66.25,
        "1W": 64.59,
        "1M": 68.41
      },
      "status": "success",
      "successful_timeframes": 3,
      "timestamp": "2025-10-01T10:12:24.484004",
      "attempts": 1
    },
    "CSELK-LUMX.N0000": {
      "rsi_data": {
        "1D": 42.3,
        "1W": 49.3,
        "1M": 47.5
      },
      "status": "success",
      "successful_timeframes": 3,
      "timestamp": "2025-10-01T10:12:40.126404",
      "attempts": 1
    },
    "CSELK-LVEF.N0000": {
      "rsi_data": {
        "1D": 63.2,
        "1W": 73.3,
        "1M": 78.8
      },
      "status": "success",
      "successful_timeframes": 3,
      "timestamp": "2025-10-01T10:12:56.313545",
      "attempts": 1
    },
    "CSELK-LVEN.N0000": {
      "rsi_data": {
        "1D": 43.3,
        "1W": 65.8,
        "1M": 71.9
      },
      "status": "success",
      "successful_timeframes": 3,
      "timestamp": "2025-10-01T10:13:11.789639",
      "attempts": 1
    },
    "CSELK-LWL.N0000": {
      "rsi_data": {
        "1D": 56.7,
        "1W": 53.1,
        "1M": 50.8
      },
      "status": "success",
      "successful_timeframes": 3,
      "timestamp": "2025-10-01T10:13:27.557173",
      "attempts": 1
    },
    "CSELK-MADU.N0000": {
      "rsi_data": {
        "1D": 57.7,
        "1W": 60.4,
        "1M": 58.3
      },
      "status": "success",
      "successful_timeframes": 3,
      "timestamp": "2025-10-01T10:13:43.333918",
      "attempts": 1
    },
    "CSELK-MAL.N0000": {
      "rsi_data": {
        "1D": 56.5,
        "1W": 53.8,
        "1M": 54.1
      },
      "status": "success",
      "successful_timeframes": 3,
      "timestamp": "2025-10-01T10:13:59.738895",
      "attempts": 1
    },
    "CSELK-MAL.X0000": {
      "rsi_data": {
        "1D": 61.9,
        "1W": 64.5,
        "1M": 61.5
      },
      "status": "success",
      "successful_timeframes": 3,
      "timestamp": "2025-10-01T10:14:15.256505",
      "attempts": 1
    },
    "CSELK-MAWA.N0000": {
      "rsi_data": null,
      "status": "failed",
      "error": "Page did not load properly (attempt 3)",
      "timestamp": "2025-10-01T10:16:32.260831",
      "attempts": 3
    },
    "CSELK-MASK.N0000": {
      "rsi_data": {
        "1D": 71.03,
        "1W": 76.29,
        "1M": 80.07
      },
      "status": "success",
      "successful_timeframes": 3,
      "timestamp": "2025-10-01T10:16:48.165974",
      "attempts": 1
    },
    "CSELK-MBSL.N0000": {
      "rsi_data": {
        "1D": 56.7,
        "1W": 65.0,
        "1M": 69.7
      },
      "status": "success",
      "successful_timeframes": 3,
      "timestamp": "2025-10-01T10:17:04.381692",
      "attempts": 1
    },
    "CSELK-MCPL.N0000": {
      "rsi_data": {
        "1D": 48.2,
        "1W": 66.1,
        "1M": 67.3
      },
      "status": "success",
      "successful_timeframes": 3,
      "timestamp": "2025-10-01T10:17:19.861372",
      "attempts": 1
    },
    "CSELK-MDL.N0000": {
      "rsi_data": {
        "1D": 64.8,
        "1W": 76.1,
        "1M": 72.9
      },
      "status": "success",
      "successful_timeframes": 3,
      "timestamp": "2025-10-01T10:17:35.883234",
      "attempts": 1
    },
    "CSELK-MEL.N0000": {
      "rsi_data": {
        "1D": 56.8,
        "1W": 69.5,
        "1M": 72.0
      },
      "status": "success",
      "successful_timeframes": 3,
      "timestamp": "2025-10-01T10:17:51.344593",
      "attempts": 1
    },
    "CSELK-MELS.N0000": {
      "rsi_data": {
        "1D": 74.18,
        "1W": 77.4,
        "1M": 82.52
      },
      "status": "success",
      "successful_timeframes": 3,
      "timestamp": "2025-10-01T10:18:07.190473",
      "attempts": 1
    },
    "CSELK-MERC.N0000": {
      "rsi_data": null,
      "status": "failed",
      "error": "Page did not load properly (attempt 3)",
      "timestamp": "2025-10-01T10:20:24.847348",
      "attempts": 3
    },
    "CSELK-MFPE.N0000": {
      "rsi_data": {
        "1D": 55.4,
        "1W": 70.3,
        "1M": 88.6
      },
      "status": "success",
      "successful_timeframes": 3,
      "timestamp": "2025-10-01T10:20:39.889372",
      "attempts": 1
    },
    "CSELK-MGT.N0000": {
      "rsi_data": {
        "1D": 47.7,
        "1W": 46.9,
        "1M": 51.2
      },
      "status": "success",
      "successful_timeframes": 3,
      "timestamp": "2025-10-01T10:20:55.297689",
      "attempts": 1
    },
    "CSELK-MHDL.N0000": {
      "rsi_data": {
        "1D": 47.4,
        "1W": 62.0,
        "1M": 75.7
      },
      "status": "success",
      "successful_timeframes": 3,
      "timestamp": "2025-10-01T10:21:10.685090",
      "attempts": 1
    },
    "CSELK-MRH.N0000": {
      "rsi_data": {
        "1D": 60.3,
        "1W": 63.4,
        "1M": 69.7
      },
      "status": "success",
      "successful_timeframes": 3,
      "timestamp": "2025-10-01T10:21:26.542345",
      "attempts": 1
    },
    "CSELK-MSL.N0000": {
      "rsi_data": {
        "1D": 83.02,
        "1W": 83.4,
        "1M": 81.18
      },
      "status": "success",
      "successful_timeframes": 3,
      "timestamp": "2025-10-01T10:21:43.027609",
      "attempts": 1
    },
    "CSELK-MULL.N0000": {
      "rsi_data": {
        "1D": 52.8,
        "1W": 59.6,
        "1M": 68.5
      },
      "status": "success",
      "successful_timeframes": 3,
      "timestamp": "2025-10-01T10:22:02.798491",
      "attempts": 1
    },
    "CSELK-NAMU.N0000": {
      "rsi_data": {
        "1D": 73.43,
        "1W": 80.08,
        "1M": 76.53
      },
      "status": "success",
      "successful_timeframes": 3,
      "timestamp": "2025-10-01T10:22:18.525264",
      "attempts": 1
    },
    "CSELK-NAVF.U0000": {
      "rsi_data": {
        "1D": 53.4,
        "1W": 53.2,
        "1M": null
      },
      "status": "success",
      "successful_timeframes": 2,
      "timestamp": "2025-10-01T10:23:15.419512",
      "attempts": 1
    },
    "CSELK-NDB.N0000": {
      "rsi_data": {
        "1D": 56.39,
        "1W": 69.71,
        "1M": 73.63
      },
      "status": "success",
      "successful_timeframes": 3,
      "timestamp": "2025-10-01T10:23:30.973217",
      "attempts": 1
    },
    "CSELK-NHL.N0000": {
      "rsi_data": {
        "1D": 57.2,
        "1W": 79.2,
        "1M": 75.4
      },
      "status": "success",
      "successful_timeframes": 3,
      "timestamp": "2025-10-01T10:23:47.058184",
      "attempts": 1
    },
    "CSELK-NTB.N0000": {
      "rsi_data": {
        "1D": 76.94,
        "1W": 86.08,
        "1M": 89.41
      },
      "status": "success",
      "successful_timeframes": 3,
      "timestamp": "2025-10-01T10:24:02.188896",
      "attempts": 1
    },
    "CSELK-NTB.X0000": {
      "rsi_data": {
        "1D": 74.68,
        "1W": 72.2,
        "1M": 79.51
      },
      "status": "success",
      "successful_timeframes": 3,
      "timestamp": "2025-10-01T10:24:18.038266",
      "attempts": 1
    },
    "CSELK-PACK.N0000": {
      "rsi_data": {
        "1D": 48.7,
        "1W": 52.0,
        "1M": 49.2
      },
      "status": "success",
      "successful_timeframes": 3,
      "timestamp": "2025-10-01T10:24:33.653420",
      "attempts": 1
    },
    "CSELK-SHAW.N0000": {
      "rsi_data": {
        "1D": 45.98,
        "1W": 63.63,
        "1M": 75.55
      },
      "status": "success",
      "successful_timeframes": 3,
      "timestamp": "2025-10-01T10:24:49.789288",
      "attempts": 1
    },
    "CSELK-TILE.N0000": {
      "rsi_data": {
        "1D": 48.0,
        "1W": 45.6,
        "1M": 50.9
      },
      "status": "success",
      "successful_timeframes": 3,
      "timestamp": "2025-10-01T10:25:06.165756",
      "attempts": 1
    },
    "CSELK-TYRE.N0000": {
      "rsi_data": {
        "1D": 46.2,
        "1W": 57.8,
        "1M": 64.1
      },
      "status": "success",
      "successful_timeframes": 3,
      "timestamp": "2025-10-01T10:25:21.985677",
      "attempts": 1
    },
    "CSELK-WAPO.N0000": {
      "rsi_data": {
        "1D": 66.8,
        "1W": 78.0,
        "1M": 81.6
      },
      "status": "success",
      "successful_timeframes": 3,
      "timestamp": "2025-10-01T10:25:37.860399",
      "attempts": 1
    },
    "CSELK-AAIC.N0000": {
      "rsi_data": {
        "1D": 42.2,
        "1W": 51.0,
        "1M": 53.7
      },
      "status": "success",
      "successful_timeframes": 3,
      "timestamp": "2025-10-01T10:25:53.867864",
      "attempts": 1
    },
    "CSELK-AUTO.N0000": {
      "rsi_data": {
        "1D": 74.88,
        "1W": 74.33,
        "1M": 66.6
      },
      "status": "success",
      "successful_timeframes": 3,
      "timestamp": "2025-10-01T10:26:09.653866",
      "attempts": 1
    },
    "CSELK-CARE.N0000": {
      "rsi_data": {
        "1D": 46.8,
        "1W": 45.9,
        "1M": 53.0
      },
      "status": "success",
      "successful_timeframes": 3,
      "timestamp": "2025-10-01T10:26:25.131919",
      "attempts": 1
    },
    "CSELK-CFLB.N0000": {
      "rsi_data": {
        "1D": 55.4,
        "1W": 64.6,
        "1M": 77.0
      },
      "status": "success",
      "successful_timeframes": 3,
      "timestamp": "2025-10-01T10:26:41.238454",
      "attempts": 1
    },
    "CSELK-COCO.N0000": {
      "rsi_data": {
        "1D": 59.3,
        "1W": 74.5,
        "1M": 66.4
      },
      "status": "success",
      "successful_timeframes": 3,
      "timestamp": "2025-10-01T10:26:56.972078",
      "attempts": 1
    },
    "CSELK-COCO.X0000": {
      "rsi_data": {
        "1D": 50.4,
        "1W": 66.7,
        "1M": 64.8
      },
      "status": "success",
      "successful_timeframes": 3,
      "timestamp": "2025-10-01T10:27:12.787805",
      "attempts": 1
    },
    "CSELK-COF.U0000": {
      "rsi_data": {
        "1D": 55.2,
        "1W": 54.2,
        "1M": 50.7
      },
      "status": "success",
      "successful_timeframes": 3,
      "timestamp": "2025-10-01T10:27:28.922599",
      "attempts": 1
    },
    "CSELK-CRL.N0000": {
      "rsi_data": {
        "1D": 48.9,
        "1W": 47.1,
        "1M": 43.2
      },
      "status": "success",
      "successful_timeframes": 3,
      "timestamp": "2025-10-01T10:27:44.571103",
      "attempts": 1
    },
    "CSELK-CSD.N0000": {
      "rsi_data": {
        "1D": 39.8,
        "1W": 51.0,
        "1M": 64.4
      },
      "status": "success",
      "successful_timeframes": 3,
      "timestamp": "2025-10-01T10:28:00.579099",
      "attempts": 1
    },
    "CSELK-GLAS.N0000": {
      "rsi_data": {
        "1D": 60.2,
        "1W": 75.9,
        "1M": 90.5
      },
      "status": "success",
      "successful_timeframes": 3,
      "timestamp": "2025-10-01T10:28:16.411919",
      "attempts": 1
    },
    "CSELK-HPWR.N0000": {
      "rsi_data": {
        "1D": 61.1,
        "1W": 79.7,
        "1M": 79.1
      },
      "status": "success",
      "successful_timeframes": 3,
      "timestamp": "2025-10-01T10:28:31.518114",
      "attempts": 1
    },
    "CSELK-IDL.N0000": {
      "rsi_data": {
        "1D": 29.3,
        "1W": 28.3,
        "1M": 36.3
      },
      "status": "success",
      "successful_timeframes": 3,
      "timestamp": "2025-10-01T10:28:47.226740",
      "attempts": 1
    },
    "CSELK-KHC.N0000": {
      "rsi_data": {
        "1D": 77.4,
        "1W": 81.4,
        "1M": 85.0
      },
      "status": "success",
      "successful_timeframes": 3,
      "timestamp": "2025-10-01T10:29:03.015553",
      "attempts": 1
    },
    "CSELK-LHCL.N0000": {
      "rsi_data": {
        "1D": 71.7,
        "1W": 71.4,
        "1M": 57.4
      },
      "status": "success",
      "successful_timeframes": 3,
      "timestamp": "2025-10-01T10:29:19.162210",
      "attempts": 1
    },
    "CSELK-LHL.N0000": {
      "rsi_data": {
        "1D": 51.9,
        "1W": 68.6,
        "1M": 84.0
      },
      "status": "success",
      "successful_timeframes": 3,
      "timestamp": "2025-10-01T10:29:34.555454",
      "attempts": 1
    },
    "CSELK-NEH.N0000": {
      "rsi_data": {
        "1D": 65.26,
        "1W": 75.27,
        "1M": 85.55
      },
      "status": "success",
      "successful_timeframes": 3,
      "timestamp": "2025-10-01T10:29:50.510452",
      "attempts": 1
    },
    "CSELK-ODEL.N0000": {
      "rsi_data": {
        "1D": 52.0,
        "1W": 54.9,
        "1M": 44.7
      },
      "status": "success",
      "successful_timeframes": 3,
      "timestamp": "2025-10-01T10:30:06.396623",
      "attempts": 1
    },
    "CSELK-OFEQ.N0000": {
      "rsi_data": {
        "1D": 54.53,
        "1W": 54.14,
        "1M": 59.22
      },
      "status": "success",
      "successful_timeframes": 3,
      "timestamp": "2025-10-01T10:30:21.959473",
      "attempts": 1
    },
    "CSELK-ONAL.N0000": {
      "rsi_data": {
        "1D": 54.4,
        "1W": 71.3,
        "1M": 75.6
      },
      "status": "success",
      "successful_timeframes": 3,
      "timestamp": "2025-10-01T10:30:37.207325",
      "attempts": 1
    },
    "CSELK-OSEA.N0000": {
      "rsi_data": {
        "1D": 56.1,
        "1W": 74.8,
        "1M": 84.7
      },
      "status": "success",
      "successful_timeframes": 3,
      "timestamp": "2025-10-01T10:30:53.009848",
      "attempts": 1
    },
    "CSELK-PABC.N0000": {
      "rsi_data": {
        "1D": 73.5,
        "1W": 90.9,
        "1M": 86.7
      },
      "status": "success",
      "successful_timeframes": 3,
      "timestamp": "2025-10-01T10:31:09.348487",
      "attempts": 1
    },
    "CSELK-PALM.N0000": {
      "rsi_data": {
        "1D": 50.3,
        "1W": 56.1,
        "1M": 63.7
      },
      "status": "success",
      "successful_timeframes": 3,
      "timestamp": "2025-10-01T10:31:24.987423",
      "attempts": 1
    },
    "CSELK-PAP.N0000": {
      "rsi_data": {
        "1D": 77.8,
        "1W": 85.5,
        "1M": 93.7
      },
      "status": "success",
      "successful_timeframes": 3,
      "timestamp": "2025-10-01T10:31:40.989101",
      "attempts": 1
    },
    "CSELK-PARA.N0000": {
      "rsi_data": {
        "1D": 68.23,
        "1W": 70.95,
        "1M": 71.39
      },
      "status": "success",
      "successful_timeframes": 3,
      "timestamp": "2025-10-01T10:31:57.032166",
      "attempts": 1
    },
    "CSELK-PARQ.N0000": {
      "rsi_data": {
        "1D": 53.3,
        "1W": 63.1,
        "1M": 79.4
      },
      "status": "success",
      "successful_timeframes": 3,
      "timestamp": "2025-10-01T10:32:12.102815",
      "attempts": 1
    },
    "CSELK-PEG.N0000": {
      "rsi_data": {
        "1D": 62.0,
        "1W": 73.5,
        "1M": 71.7
      },
      "status": "success",
      "successful_timeframes": 3,
      "timestamp": "2025-10-01T10:32:27.208896",
      "attempts": 1
    },
    "CSELK-PINS.N0000": {
      "rsi_data": {
        "1D": 60.9,
        "1W": 63.3,
        "1M": 70.1
      },
      "status": "success",
      "successful_timeframes": 3,
      "timestamp": "2025-10-01T10:32:43.491649",
      "attempts": 1
    },
    "CSELK-PLC.N0000": {
      "rsi_data": {
        "1D": 77.4,
        "1W": 80.2,
        "1M": 83.1
      },
      "status": "success",
      "successful_timeframes": 3,
      "timestamp": "2025-10-01T10:32:59.456794",
      "attempts": 1
    },
    "CSELK-PLR.N0000": {
      "rsi_data": {
        "1D": 70.9,
        "1W": 88.7,
        "1M": 89.3
      },
      "status": "success",
      "successful_timeframes": 3,
      "timestamp": "2025-10-01T10:33:16.028441",
      "attempts": 1
    },
    "CSELK-PMB.N0000": {
      "rsi_data": {
        "1D": 45.0,
        "1W": 63.8,
        "1M": 72.5
      },
      "status": "success",
      "successful_timeframes": 3,
      "timestamp": "2025-10-01T10:33:31.933928",
      "attempts": 1
    },
    "CSELK-RAL.N0000": {
      "rsi_data": {
        "1D": 63.7,
        "1W": 72.0,
        "1M": 66.4
      },
      "status": "success",
      "successful_timeframes": 3,
      "timestamp": "2025-10-01T10:33:48.241985",
      "attempts": 1
    },
    "CSELK-RCH.N0000": {
      "rsi_data": {
        "1D": 54.3,
        "1W": 74.48,
        "1M": 80.59
      },
      "status": "success",
      "successful_timeframes": 3,
      "timestamp": "2025-10-01T10:34:04.452471",
      "attempts": 1
    },
    "CSELK-RCL.N0000": {
      "rsi_data": {
        "1D": 57.2,
        "1W": 65.9,
        "1M": 63.0
      },
      "status": "success",
      "successful_timeframes": 3,
      "timestamp": "2025-10-01T10:34:19.761275",
      "attempts": 1
    },
    "CSELK-RENU.N0000": {
      "rsi_data": {
        "1D": 67.84,
        "1W": 73.12,
        "1M": 83.15
      },
      "status": "success",
      "successful_timeframes": 3,
      "timestamp": "2025-10-01T10:34:35.932525",
      "attempts": 1
    },
    "CSELK-REXP.N0000": {
      "rsi_data": {
        "1D": 49.25,
        "1W": 48.35,
        "1M": 39.1
      },
      "status": "success",
      "successful_timeframes": 3,
      "timestamp": "2025-10-01T10:34:52.066109",
      "attempts": 1
    },
    "CSELK-RFL.N0000": {
      "rsi_data": {
        "1D": 58.0,
        "1W": 65.5,
        "1M": 72.6
      },
      "status": "success",
      "successful_timeframes": 3,
      "timestamp": "2025-10-01T10:35:08.103510",
      "attempts": 1
    },
    "CSELK-RGEM.N0000": {
      "rsi_data": {
        "1D": 51.7,
        "1W": 53.2,
        "1M": 52.4
      },
      "status": "success",
      "successful_timeframes": 3,
      "timestamp": "2025-10-01T10:35:23.562863",
      "attempts": 1
    },
    "CSELK-RHL.N0000": {
      "rsi_data": {
        "1D": 66.2,
        "1W": 77.8,
        "1M": 76.0
      },
      "status": "success",
      "successful_timeframes": 3,
      "timestamp": "2025-10-01T10:35:39.585781",
      "attempts": 1
    },
    "CSELK-RHL.X0000": {
      "rsi_data": {
        "1D": 57.1,
        "1W": 76.0,
        "1M": 75.0
      },
      "status": "success",
      "successful_timeframes": 3,
      "timestamp": "2025-10-01T10:35:59.468917",
      "attempts": 1
    },
    "CSELK-RHTL.N0000": {
      "rsi_data": {
        "1D": 67.2,
        "1W": 68.5,
        "1M": 68.0
      },
      "status": "success",
      "successful_timeframes": 3,
      "timestamp": "2025-10-01T10:36:15.512643",
      "attempts": 1
    },
    "CSELK-RICH.N0000": {
      "rsi_data": {
        "1D": 52.7,
        "1W": 57.4,
        "1M": 59.9
      },
      "status": "success",
      "successful_timeframes": 3,
      "timestamp": "2025-10-01T10:36:31.560499",
      "attempts": 1
    },
    "CSELK-RIL.N0000": {
      "rsi_data": {
        "1D": 72.3,
        "1W": 82.6,
        "1M": 89.4
      },
      "status": "success",
      "successful_timeframes": 3,
      "timestamp": "2025-10-01T10:36:47.937380",
      "attempts": 1
    },
    "CSELK-RPBH.N0000": {
      "rsi_data": {
        "1D": 51.0,
        "1W": 76.0,
        "1M": 75.1
      },
      "status": "success",
      "successful_timeframes": 3,
      "timestamp": "2025-10-01T10:37:04.274706",
      "attempts": 1
    },
    "CSELK-RWSL.N0000": {
      "rsi_data": {
        "1D": 64.4,
        "1W": 81.0,
        "1M": 91.5
      },
      "status": "success",
      "successful_timeframes": 3,
      "timestamp": "2025-10-01T10:37:20.293452",
      "attempts": 1
    },
    "CSELK-SAMP.N0000": {
      "rsi_data": {
        "1D": 59.6,
        "1W": 70.59,
        "1M": 77.58
      },
      "status": "success",
      "successful_timeframes": 3,
      "timestamp": "2025-10-01T10:37:36.036063",
      "attempts": 1
    },
    "CSELK-SCAP.N0000": {
      "rsi_data": {
        "1D": 45.9,
        "1W": 47.1,
        "1M": 44.6
      },
      "status": "success",
      "successful_timeframes": 3,
      "timestamp": "2025-10-01T10:37:51.681634",
      "attempts": 1
    },
    "CSELK-SDB.N0000": {
      "rsi_data": {
        "1D": 57.3,
        "1W": 63.7,
        "1M": 64.9
      },
      "status": "success",
      "successful_timeframes": 3,
      "timestamp": "2025-10-01T10:38:07.645444",
      "attempts": 1
    },
    "CSELK-SDF.N0000": {
      "rsi_data": {
        "1D": 47.7,
        "1W": 60.0,
        "1M": 74.3
      },
      "status": "success",
      "successful_timeframes": 3,
      "timestamp": "2025-10-01T10:38:23.024105",
      "attempts": 1
    },
    "CSELK-SEMB.N0000": {
      "rsi_data": {
        "1D": 43.2,
        "1W": 47.5,
        "1M": 49.0
      },
      "status": "success",
      "successful_timeframes": 3,
      "timestamp": "2025-10-01T10:38:39.109390",
      "attempts": 1
    },
    "CSELK-SEMB.X0000": {
      "rsi_data": {
        "1D": 53.5,
        "1W": 57.9,
        "1M": 56.9
      },
      "status": "success",
      "successful_timeframes": 3,
      "timestamp": "2025-10-01T10:38:55.889842",
      "attempts": 1
    },
    "CSELK-SERV.N0000": {
      "rsi_data": {
        "1D": 73.4,
        "1W": 81.2,
        "1M": 80.9
      },
      "status": "success",
      "successful_timeframes": 3,
      "timestamp": "2025-10-01T10:39:11.539890",
      "attempts": 1
    },
    "CSELK-SEYB.N0000": {
      "rsi_data": {
        "1D": 52.0,
        "1W": 67.5,
        "1M": 74.0
      },
      "status": "success",
      "successful_timeframes": 3,
      "timestamp": "2025-10-01T10:39:27.667983",
      "attempts": 1
    },
    "CSELK-SEYB.X0000": {
      "rsi_data": {
        "1D": 51.1,
        "1W": 66.8,
        "1M": 73.0
      },
      "status": "success",
      "successful_timeframes": 3,
      "timestamp": "2025-10-01T10:39:43.428398",
      "attempts": 1
    },
    "CSELK-SFCL.N0000": {
      "rsi_data": {
        "1D": 60.7,
        "1W": 63.85,
        "1M": 69.52
      },
      "status": "success",
      "successful_timeframes": 3,
      "timestamp": "2025-10-01T10:39:58.919016",
      "attempts": 1
    },
    "CSELK-SFIN.N0000": {
      "rsi_data": {
        "1D": 64.3,
        "1W": 78.0,
        "1M": 92.6
      },
      "status": "success",
      "successful_timeframes": 3,
      "timestamp": "2025-10-01T10:40:14.761042",
      "attempts": 1
    },
    "CSELK-SHL.N0000": {
      "rsi_data": {
        "1D": 41.5,
        "1W": 38.4,
        "1M": 40.6
      },
      "status": "success",
      "successful_timeframes": 3,
      "timestamp": "2025-10-01T10:40:30.410099",
      "attempts": 1
    },
    "CSELK-SHL.W0000": {
      "rsi_data": null,
      "status": "failed",
      "error": "Page did not load properly (attempt 3)",
      "timestamp": "2025-10-01T10:42:48.523711",
      "attempts": 3
    },
    "CSELK-SHOT.N0000": {
      "rsi_data": {
        "1D": 59.4,
        "1W": 64.5,
        "1M": 69.7
      },
      "status": "success",
      "successful_timeframes": 3,
      "timestamp": "2025-10-01T10:43:03.912165",
      "attempts": 1
    },
    "CSELK-SHOT.X0000": {
      "rsi_data": {
        "1D": 66.4,
        "1W": 68.3,
        "1M": 73.2
      },
      "status": "success",
      "successful_timeframes": 3,
      "timestamp": "2025-10-01T10:43:19.994373",
      "attempts": 1
    },
    "CSELK-SIGV.N0000": {
      "rsi_data": {
        "1D": 49.16,
        "1W": 59.08,
        "1M": 73.73
      },
      "status": "success",
      "successful_timeframes": 3,
      "timestamp": "2025-10-01T10:43:35.616534",
      "attempts": 1
    },
    "CSELK-SIL.N0000": {
      "rsi_data": {
        "1D": 72.92,
        "1W": 83.8,
        "1M": 71.8
      },
      "status": "success",
      "successful_timeframes": 3,
      "timestamp": "2025-10-01T10:43:50.695331",
      "attempts": 1
    },
    "CSELK-SING.N0000": {
      "rsi_data": {
        "1D": 30.5,
        "1W": 51.0,
        "1M": 52.1
      },
      "status": "success",
      "successful_timeframes": 3,
      "timestamp": "2025-10-01T10:44:07.525512",
      "attempts": 1
    },
    "CSELK-SINH.N0000": {
      "rsi_data": {
        "1D": 60.5,
        "1W": 68.9,
        "1M": 78.3
      },
      "status": "success",
      "successful_timeframes": 3,
      "timestamp": "2025-10-01T10:44:25.757531",
      "attempts": 1
    },
    "CSELK-SINS.N0000": {
      "rsi_data": {
        "1D": 72.9,
        "1W": 83.5,
        "1M": 91.5
      },
      "status": "success",
      "successful_timeframes": 3,
      "timestamp": "2025-10-01T10:44:41.858721",
      "attempts": 1
    },
    "CSELK-SIRA.N0000": {
      "rsi_data": {
        "1D": 52.2,
        "1W": 65.9,
        "1M": 78.0
      },
      "status": "success",
      "successful_timeframes": 3,
      "timestamp": "2025-10-01T10:44:57.390811",
      "attempts": 1
    },
    "CSELK-SLND.N0000": {
      "rsi_data": {
        "1D": 45.86,
        "1W": 54.64,
        "1M": 54.95
      },
      "status": "success",
      "successful_timeframes": 3,
      "timestamp": "2025-10-01T10:45:12.563210",
      "attempts": 1
    },
    "CSELK-SLTL.N0000": {
      "rsi_data": {
        "1D": 53.1,
        "1W": 55.9,
        "1M": 47.2
      },
      "status": "success",
      "successful_timeframes": 3,
      "timestamp": "2025-10-01T10:45:28.522119",
      "attempts": 1
    },
    "CSELK-SMOT.N0000": {
      "rsi_data": {
        "1D": 70.06,
        "1W": 78.57,
        "1M": 83.46
      },
      "status": "success",
      "successful_timeframes": 3,
      "timestamp": "2025-10-01T10:45:44.362578",
      "attempts": 1
    },
    "CSELK-SUN.N0000": {
      "rsi_data": {
        "1D": 70.4,
        "1W": 78.6,
        "1M": 81.6
      },
      "status": "success",
      "successful_timeframes": 3,
      "timestamp": "2025-10-01T10:46:00.545474",
      "attempts": 1
    },
    "CSELK-SWAD.N0000": {
      "rsi_data": {
        "1D": 56.26,
        "1W": 58.9,
        "1M": 60.29
      },
      "status": "success",
      "successful_timeframes": 3,
      "timestamp": "2025-10-01T10:46:16.920187",
      "attempts": 1
    },
    "CSELK-TAFL.N0000": {
      "rsi_data": {
        "1D": 66.87,
        "1W": 69.7,
        "1M": 75.35
      },
      "status": "success",
      "successful_timeframes": 3,
      "timestamp": "2025-10-01T10:46:33.284548",
      "attempts": 1
    },
    "CSELK-TAJ.N0000": {
      "rsi_data": {
        "1D": 52.8,
        "1W": 76.9,
        "1M": 77.5
      },
      "status": "success",
      "successful_timeframes": 3,
      "timestamp": "2025-10-01T10:46:49.338506",
      "attempts": 1
    },
    "CSELK-TANG.N0000": {
      "rsi_data": {
        "1D": 56.43,
        "1W": 72.0,
        "1M": 79.59
      },
      "status": "success",
      "successful_timeframes": 3,
      "timestamp": "2025-10-01T10:47:04.700982",
      "attempts": 1
    },
    "CSELK-TESS.N0000": {
      "rsi_data": {
        "1D": 58.5,
        "1W": 64.2,
        "1M": 67.1
      },
      "status": "success",
      "successful_timeframes": 3,
      "timestamp": "2025-10-01T10:47:20.767343",
      "attempts": 1
    },
    "CSELK-TESS.X0000": {
      "rsi_data": {
        "1D": 50.5,
        "1W": 56.5,
        "1M": 62.6
      },
      "status": "success",
      "successful_timeframes": 3,
      "timestamp": "2025-10-01T10:47:36.762735",
      "attempts": 1
    },
    "CSELK-TJL.N0000": {
      "rsi_data": {
        "1D": 29.3,
        "1W": 34.1,
        "1M": 47.5
      },
      "status": "success",
      "successful_timeframes": 3,
      "timestamp": "2025-10-01T10:47:52.386660",
      "attempts": 1
    },
    "CSELK-TKYO.N0000": {
      "rsi_data": {
        "1D": 64.6,
        "1W": 63.1,
        "1M": 73.1
      },
      "status": "success",
      "successful_timeframes": 3,
      "timestamp": "2025-10-01T10:48:08.777803",
      "attempts": 1
    },
    "CSELK-TKYO.X0000": {
      "rsi_data": {
        "1D": 58.6,
        "1W": 63.4,
        "1M": 70.3
      },
      "status": "success",
      "successful_timeframes": 3,
      "timestamp": "2025-10-01T10:48:24.395315",
      "attempts": 1
    },
    "CSELK-TPL.N0000": {
      "rsi_data": {
        "1D": 66.34,
        "1W": 73.33,
        "1M": 70.97
      },
      "status": "success",
      "successful_timeframes": 3,
      "timestamp": "2025-10-01T10:48:40.365940",
      "attempts": 1
    },
    "CSELK-TRAN.N0000": {
      "rsi_data": {
        "1D": 69.6,
        "1W": 78.5,
        "1M": 73.4
      },
      "status": "success",
      "successful_timeframes": 3,
      "timestamp": "2025-10-01T10:48:55.973264",
      "attempts": 1
    },
    "CSELK-TSML.N0000": {
      "rsi_data": {
        "1D": 60.1,
        "1W": 68.9,
        "1M": 64.4
      },
      "status": "success",
      "successful_timeframes": 3,
      "timestamp": "2025-10-01T10:49:11.724102",
      "attempts": 1
    },
    "CSELK-UAL.N0000": {
      "rsi_data": {
        "1D": 60.3,
        "1W": 68.0,
        "1M": 73.7
      },
      "status": "success",
      "successful_timeframes": 3,
      "timestamp": "2025-10-01T10:49:28.021263",
      "attempts": 1
    },
    "CSELK-UBC.N0000": {
      "rsi_data": {
        "1D": 58.8,
        "1W": 71.4,
        "1M": 70.8
      },
      "status": "success",
      "successful_timeframes": 3,
      "timestamp": "2025-10-01T10:49:43.217910",
      "attempts": 1
    },
    "CSELK-UBF.N0000": {
      "rsi_data": {
        "1D": 64.7,
        "1W": 79.7,
        "1M": 85.5
      },
      "status": "success",
      "successful_timeframes": 3,
      "timestamp": "2025-10-01T10:49:59.365204",
      "attempts": 1
    },
    "CSELK-UCAR.N0000": {
      "rsi_data": {
        "1D": 61.27,
        "1W": 78.49,
        "1M": 75.09
      },
      "status": "success",
      "successful_timeframes": 3,
      "timestamp": "2025-10-01T10:50:15.164615",
      "attempts": 1
    },
    "CSELK-UDPL.N0000": {
      "rsi_data": {
        "1D": 63.68,
        "1W": 75.78,
        "1M": 72.03
      },
      "status": "success",
      "successful_timeframes": 3,
      "timestamp": "2025-10-01T10:50:30.361933",
      "attempts": 1
    },
    "CSELK-UML.N0000": {
      "rsi_data": {
        "1D": 85.93,
        "1W": 83.0,
        "1M": 87.66
      },
      "status": "success",
      "successful_timeframes": 3,
      "timestamp": "2025-10-01T10:50:46.747973",
      "attempts": 1
    },
    "CSELK-VFIN.N0000": {
      "rsi_data": {
        "1D": 50.27,
        "1W": 66.88,
        "1M": 84.37
      },
      "status": "success",
      "successful_timeframes": 3,
      "timestamp": "2025-10-01T10:51:02.824569",
      "attempts": 1
    },
    "CSELK-VLL.N0000": {
      "rsi_data": {
        "1D": 55.8,
        "1W": 74.3,
        "1M": 86.4
      },
      "status": "success",
      "successful_timeframes": 3,
      "timestamp": "2025-10-01T10:51:22.871025",
      "attempts": 1
    },
    "CSELK-VLL.X0000": {
      "rsi_data": {
        "1D": 56.4,
        "1W": 85.2,
        "1M": 88.4
      },
      "status": "success",
      "successful_timeframes": 3,
      "timestamp": "2025-10-01T10:51:38.746854",
      "attempts": 1
    },
    "CSELK-VONE.N0000": {
      "rsi_data": {
        "1D": 60.34,
        "1W": 73.37,
        "1M": 73.44
      },
      "status": "success",
      "successful_timeframes": 3,
      "timestamp": "2025-10-01T10:51:54.139113",
      "attempts": 1
    },
    "CSELK-VPEL.N0000": {
      "rsi_data": {
        "1D": 70.7,
        "1W": 82.1,
        "1M": 84.4
      },
      "status": "success",
      "successful_timeframes": 3,
      "timestamp": "2025-10-01T10:52:09.643718",
      "attempts": 1
    }
  },
  "failed_symbols": [
    "CSELK-ASPM.N0000",
    "CSELK-AMCL.N0000",
    "CSELK-HNBF.R0000",
    "CSELK-HNBF.R0001",
    "CSELK-MAWA.N0000",
    "CSELK-MERC.N0000",
    "CSELK-SHL.W0000"
  ]
}